{
  "last_update": "23/3/2026, 12.08.13 WIB",
  "ongoing_anime": [
    {
      "title": "Sousou no Frieren 2nd Season",
      "image": "https://myanimelist.net/images/anime/1921/154528.jpg",
      "score": 9.04,
      "episodes": 10,
      "url": "https://myanimelist.net/anime/59978/Sousou_no_Frieren_2nd_Season"
    },
    {
      "title": "Jujutsu Kaisen: Shimetsu Kaiyuu - Zenpen",
      "image": "https://myanimelist.net/images/anime/1659/154920.jpg",
      "score": 8.58,
      "episodes": 12,
      "url": "https://myanimelist.net/anime/57658/Jujutsu_Kaisen__Shimetsu_Kaiyuu_-_Zenpen"
    },
    {
      "title": "Jigokuraku 2nd Season",
      "image": "https://myanimelist.net/images/anime/1772/154456.jpg",
      "score": 8.24,
      "episodes": 12,
      "url": "https://myanimelist.net/anime/55825/Jigokuraku_2nd_Season"
    },
    {
      "title": "Yuusha-kei ni Shosu: Choubatsu Yuusha 9004-tai Keimu Kiroku",
      "image": "https://myanimelist.net/images/anime/1062/151911.jpg",
      "score": 8.13,
      "episodes": 12,
      "url": "https://myanimelist.net/anime/56009/Yuusha-kei_ni_Shosu__Choubatsu_Yuusha_9004-tai_Keimu_Kiroku"
    },
    {
      "title": "[Oshi no Ko] 3rd Season",
      "image": "https://myanimelist.net/images/anime/1979/153329.jpg",
      "score": 8.6,
      "episodes": 11,
      "url": "https://myanimelist.net/anime/60058/Oshi_no_Ko_3rd_Season"
    },
    {
      "title": "Enen no Shouboutai: San no Shou Part 2",
      "image": "https://myanimelist.net/images/anime/1508/152472.jpg",
      "score": 8.06,
      "episodes": 13,
      "url": "https://myanimelist.net/anime/59229/Enen_no_Shouboutai__San_no_Shou_Part_2"
    }
  ],
  "latest_releases": [
    {
      "title": "[Mo7tas] Kimi wa Houkago Insomnia [BD 1080p] [Multi language subs]",
      "link": "https://animetosho.org/view/mo7tas-kimi-wa-houkago-insomnia-bd-1080p-multi-language-subs.n2089403",
      "magnet": "magnet:?xt=urn:btih:4LF2UHTE5PDQXMSPUAAN2O46RHY6NJ26&tr=http%3A%2F%2Fnyaa.tracker.wf%3A7777%2Fannounce&tr=udp%3A%2F%2Fopen.stealth.si%3A80%2Fannounce&tr=udp%3A%2F%2Ftracker.opentrackr.org%3A1337%2Fannounce&tr=udp%3A%2F%2Fexodus.desync.com%3A6969%2Fannounce&tr=udp%3A%2F%2Ftracker.torrent.eu.org%3A451%2Fannounce&dn=%5BMo7tas%5D%20Kimi%20wa%20Houkago%20Insomnia%20%5BBD%201080p%5D%20%5BMulti%20language%20subs%5D",
      "hash": "4LF2UHTE5PDQXMSPUAAN2O46RHY6NJ26",
      "nyaaUrl": "https://nyaa.si/?q=4LF2UHTE5PDQXMSPUAAN2O46RHY6NJ26",
      "size": "NaN MB",
      "date": "23/3/2026, 11.48.04"
    },
    {
      "title": "[iiPython] Riding Bean (1989) - [1080p BD Dual-Audio OPUS AV1]",
      "link": "https://animetosho.org/view/iipython-riding-bean-1989-1080p-bd-dual-audio-opus-av1.k9869007575816",
      "magnet": "magnet:?xt=urn:btih:4ATSPYGLYVCSXAF7KMGHIAAWT6KLCJUZ&tr=https%3A%2F%2Ftracker.nekobt.to%2Fapi%2Ftracker%2Fpublic%2Fannounce&tr=udp%3A%2F%2Ftracker.opentrackr.org%3A1337%2Fannounce&tr=udp%3A%2F%2Fexodus.desync.com%3A6969%2Fannounce&tr=udp%3A%2F%2Ftracker.torrent.eu.org%3A451%2Fannounce&tr=http%3A%2F%2Ftracker.opentrackr.org%3A1337%2Fannounce&dn=%5BiiPython%5D%20Riding%20Bean%20%281989%29%20-%20%5B1080p%20BD%20Dual-Audio%20OPUS%20AV1%5D",
      "hash": "4ATSPYGLYVCSXAF7KMGHIAAWT6KLCJUZ",
      "nyaaUrl": "https://nyaa.si/?q=4ATSPYGLYVCSXAF7KMGHIAAWT6KLCJUZ",
      "size": "NaN MB",
      "date": "23/3/2026, 11.33.30"
    },
    {
      "title": "Fortune Quest L",
      "link": "https://animetosho.org/view/fortune-quest-l.n2089395",
      "magnet": "magnet:?xt=urn:btih:FNBG4VW4T4NF7WM2XXL2XRJBQMWIV2VM&tr=http%3A%2F%2Fnyaa.tracker.wf%3A7777%2Fannounce&tr=udp%3A%2F%2Ftracker.opentrackr.org%3A1337%2Fannounce&tr=http%3A%2F%2Ftracker.opentrackr.org%3A1337%2Fannounce&tr=udp%3A%2F%2Fopen.demonii.com%3A1337%2Fannounce&tr=udp%3A%2F%2Fopen.stealth.si%3A80%2Fannounce&dn=Fortune%20Quest%20L",
      "hash": "FNBG4VW4T4NF7WM2XXL2XRJBQMWIV2VM",
      "nyaaUrl": "https://nyaa.si/?q=FNBG4VW4T4NF7WM2XXL2XRJBQMWIV2VM",
      "size": "NaN MB",
      "date": "23/3/2026, 09.15.35"
    },
    {
      "title": "[ToonsHub] Star Detective Precure S01E08 REPACK 1080p CR WEB-DL AAC2.0 H.264 (Meitantei Precure!, Multi-Subs)",
      "link": "https://animetosho.org/view/toonshub-star-detective-precure-s01e08-repack-1080p-cr.n2089394",
      "magnet": "magnet:?xt=urn:btih:X5AWPICMKGAL526MPGNYAIF3B72KIZZP&tr=http%3A%2F%2Fnyaa.tracker.wf%3A7777%2Fannounce&tr=https%3A%2F%2Ftracker.nekobt.to%2Fapi%2Ftracker%2Fpublic%2Fannounce&tr=udp%3A%2F%2Ftracker.opentrackr.org%3A1337%2Fannounce&tr=udp%3A%2F%2Fexodus.desync.com%3A6969%2Fannounce&tr=udp%3A%2F%2Ftracker.torrent.eu.org%3A451%2Fannounce&dn=%5BToonsHub%5D%20Star%20Detective%20Precure%20S01E08%20REPACK%201080p%20CR%20WEB-DL%20AAC2.0%20H.264%20%28Meitantei%20Precure%21%2C%20Multi-Subs%29",
      "hash": "X5AWPICMKGAL526MPGNYAIF3B72KIZZP",
      "nyaaUrl": "https://nyaa.si/?q=X5AWPICMKGAL526MPGNYAIF3B72KIZZP",
      "size": "NaN MB",
      "date": "23/3/2026, 08.50.52"
    },
    {
      "title": "[Anime Time] Sentenced To Be A Hero (Yuusha-kei ni Shosu: Choubatsu Yuusha 9004 Tai Keimu Kiroku) - S01E07 [1080p][HEVC 10bit x265][AAC][Dual-Audio] [Multi Sub] [Weekly]",
      "link": "https://animetosho.org/view/anime-time-sentenced-hero-yuusha-kei-ni-shosu.n2089387",
      "magnet": "magnet:?xt=urn:btih:I5CKCLD3FO3DJ46IZIYKWWC3VNXLUSR2&tr=http%3A%2F%2Fnyaa.tracker.wf%3A7777%2Fannounce&tr=http%3A%2F%2Fanidex.moe%3A6969%2Fannounce&tr=udp%3A%2F%2Fopen.stealth.si%3A80%2Fannounce&tr=udp%3A%2F%2Ftracker.opentrackr.org%3A1337%2Fannounce&tr=udp%3A%2F%2Fexodus.desync.com%3A6969%2Fannounce&dn=%5BAnime%20Time%5D%20Sentenced%20To%20Be%20A%20Hero%20%28Yuusha-kei%20ni%20Shosu%3A%20Choubatsu%20Yuusha%209004%20Tai%20Keimu%20Kiroku%29%20-%20S01E07%20%5B1080p%5D%5BHEVC%2010bit%20x265%5D%5BAAC%5D%5BDual-Audio%5D%20%5BMulti%20Sub%5D%20%5BWeekly%5D",
      "hash": "I5CKCLD3FO3DJ46IZIYKWWC3VNXLUSR2",
      "nyaaUrl": "https://nyaa.si/?q=I5CKCLD3FO3DJ46IZIYKWWC3VNXLUSR2",
      "size": "NaN MB",
      "date": "23/3/2026, 07.42.37"
    },
    {
      "title": "[Anime Time] Sentenced To Be A Hero (Yuusha-kei ni Shosu: Choubatsu Yuusha 9004 Tai Keimu Kiroku) - S01E06 [1080p][HEVC 10bit x265][AAC][Dual-Audio] [Multi Sub] [Weekly]",
      "link": "https://animetosho.org/view/anime-time-sentenced-hero-yuusha-kei-ni-shosu.n2089386",
      "magnet": "magnet:?xt=urn:btih:GNZA7MNG7JE42KMB7NDSWHE2IYY7AKE3&tr=http%3A%2F%2Fnyaa.tracker.wf%3A7777%2Fannounce&tr=http%3A%2F%2Fanidex.moe%3A6969%2Fannounce&tr=udp%3A%2F%2Fopen.stealth.si%3A80%2Fannounce&tr=udp%3A%2F%2Ftracker.opentrackr.org%3A1337%2Fannounce&tr=udp%3A%2F%2Fexodus.desync.com%3A6969%2Fannounce&dn=%5BAnime%20Time%5D%20Sentenced%20To%20Be%20A%20Hero%20%28Yuusha-kei%20ni%20Shosu%3A%20Choubatsu%20Yuusha%209004%20Tai%20Keimu%20Kiroku%29%20-%20S01E06%20%5B1080p%5D%5BHEVC%2010bit%20x265%5D%5BAAC%5D%5BDual-Audio%5D%20%5BMulti%20Sub%5D%20%5BWeekly%5D",
      "hash": "GNZA7MNG7JE42KMB7NDSWHE2IYY7AKE3",
      "nyaaUrl": "https://nyaa.si/?q=GNZA7MNG7JE42KMB7NDSWHE2IYY7AKE3",
      "size": "NaN MB",
      "date": "23/3/2026, 07.33.49"
    },
    {
      "title": "[Salieri] My Dress-up Darling S2 - BD (1080p) (HDR) [Dual Audio]",
      "link": "https://animetosho.org/view/salieri-my-dress-up-darling-s2-bd-1080p.n2089383",
      "magnet": "magnet:?xt=urn:btih:3OG6KEFFLCLFIOLPXKKDNXQ4MDIZRXYG&tr=http%3A%2F%2Fnyaa.tracker.wf%3A7777%2Fannounce&tr=udp%3A%2F%2Fopen.stealth.si%3A80%2Fannounce&tr=udp%3A%2F%2Ftracker.opentrackr.org%3A1337%2Fannounce&tr=udp%3A%2F%2Fexodus.desync.com%3A6969%2Fannounce&tr=udp%3A%2F%2Ftracker.torrent.eu.org%3A451%2Fannounce&dn=%5BSalieri%5D%20My%20Dress-up%20Darling%20S2%20-%20BD%20%281080p%29%20%28HDR%29%20%5BDual%20Audio%5D",
      "hash": "3OG6KEFFLCLFIOLPXKKDNXQ4MDIZRXYG",
      "nyaaUrl": "https://nyaa.si/?q=3OG6KEFFLCLFIOLPXKKDNXQ4MDIZRXYG",
      "size": "NaN MB",
      "date": "23/3/2026, 06.31.58"
    },
    {
      "title": "[Onalrie] Yami Shibai - S16E11 [1080p WEBRip AV1].mkv",
      "link": "https://animetosho.org/view/onalrie-yami-shibai-s16e11-1080p-webrip-av1-mkv.2068949",
      "magnet": "magnet:?xt=urn:btih:JADNGXHDOBPIXLI46LMFILCE5NJGXG4I&tr=http%3A%2F%2Ftracker.onalrie.app%3A7070%2Fannounce&tr=udp%3A%2F%2Ftracker.onalrie.app%3A6969%2Fannounce&tr=http%3A%2F%2Ftracker.beeimg.com%3A6969%2Fannounce&tr=http%3A%2F%2Ftracker.mywaifu.best%3A6969%2Fannounce&tr=https%3A%2F%2Ftracker.zhuqiy.com%3A443%2Fannounce&dn=%5BOnalrie%5D%20Yami%20Shibai%20-%20S16E11%20%5B1080p%20WEBRip%20AV1%5D.mkv",
      "hash": "JADNGXHDOBPIXLI46LMFILCE5NJGXG4I",
      "nyaaUrl": "https://nyaa.si/?q=JADNGXHDOBPIXLI46LMFILCE5NJGXG4I",
      "size": "NaN MB",
      "date": "23/3/2026, 05.39.00"
    },
    {
      "title": "[One Pace][1007-1008] Wano 59 [1080p][2ED1FD82].mkv",
      "link": "https://animetosho.org/view/one-pace-1007-1008-wano-59-1080p-2ed1fd82-mkv.n2089368",
      "magnet": "magnet:?xt=urn:btih:QWISO3XISNSW6XGGRAC7BYGRK6HT6VEG&tr=http%3A%2F%2Fnyaa.tracker.wf%3A7777%2Fannounce&tr=udp%3A%2F%2Ftracker.opentrackr.org%3A1337%2Fannounce&tr=https%3A%2F%2Ftracker1.520.jp%3A443%2Fannounce&tr=udp%3A%2F%2Fopentracker.i2p.rocks%3A6969%2Fannounce&tr=udp%3A%2F%2Fopen.demonii.com%3A1337%2Fannounce&dn=%5BOne%20Pace%5D%5B1007-1008%5D%20Wano%2059%20%5B1080p%5D%5B2ED1FD82%5D.mkv",
      "hash": "QWISO3XISNSW6XGGRAC7BYGRK6HT6VEG",
      "nyaaUrl": "https://nyaa.si/?q=QWISO3XISNSW6XGGRAC7BYGRK6HT6VEG",
      "size": "NaN MB",
      "date": "23/3/2026, 04.52.42"
    },
    {
      "title": "[SubsPlease] Yasei no Last Boss ga Arawareta! (01-12) (1080p) [Batch]",
      "link": "https://animetosho.org/view/subsplease-yasei-no-last-boss-ga-arawareta-01.n2089366",
      "magnet": "magnet:?xt=urn:btih:65Y3E2BEAXRVEYPWGCLGJ2JS7QMQ3MPO&tr=http%3A%2F%2Fnyaa.tracker.wf%3A7777%2Fannounce&tr=udp%3A%2F%2Ftracker.opentrackr.org%3A1337%2Fannounce&tr=udp%3A%2F%2Fopen.stealth.si%3A80%2Fannounce&tr=udp%3A%2F%2Fexodus.desync.com%3A6969%2Fannounce&tr=udp%3A%2F%2Ftracker.torrent.eu.org%3A451%2Fannounce&dn=%5BSubsPlease%5D%20Yasei%20no%20Last%20Boss%20ga%20Arawareta%21%20%2801-12%29%20%281080p%29%20%5BBatch%5D",
      "hash": "65Y3E2BEAXRVEYPWGCLGJ2JS7QMQ3MPO",
      "nyaaUrl": "https://nyaa.si/?q=65Y3E2BEAXRVEYPWGCLGJ2JS7QMQ3MPO",
      "size": "NaN MB",
      "date": "23/3/2026, 04.26.52"
    }
  ]
}