{
  "last_update": "20/3/2026, 00.09.59 WIB",
  "ongoing_anime": [
    {
      "title": "Sousou no Frieren 2nd Season",
      "image": "https://myanimelist.net/images/anime/1921/154528.jpg",
      "score": 9.15,
      "episodes": 10,
      "url": "https://myanimelist.net/anime/59978/Sousou_no_Frieren_2nd_Season"
    },
    {
      "title": "Jujutsu Kaisen: Shimetsu Kaiyuu - Zenpen",
      "image": "https://myanimelist.net/images/anime/1659/154920.jpg",
      "score": 8.59,
      "episodes": 12,
      "url": "https://myanimelist.net/anime/57658/Jujutsu_Kaisen__Shimetsu_Kaiyuu_-_Zenpen"
    },
    {
      "title": "Jigokuraku 2nd Season",
      "image": "https://myanimelist.net/images/anime/1772/154456.jpg",
      "score": 8.24,
      "episodes": 12,
      "url": "https://myanimelist.net/anime/55825/Jigokuraku_2nd_Season"
    },
    {
      "title": "Yuusha-kei ni Shosu: Choubatsu Yuusha 9004-tai Keimu Kiroku",
      "image": "https://myanimelist.net/images/anime/1062/151911.jpg",
      "score": 8.14,
      "episodes": 12,
      "url": "https://myanimelist.net/anime/56009/Yuusha-kei_ni_Shosu__Choubatsu_Yuusha_9004-tai_Keimu_Kiroku"
    },
    {
      "title": "[Oshi no Ko] 3rd Season",
      "image": "https://myanimelist.net/images/anime/1979/153329.jpg",
      "score": 8.6,
      "episodes": 11,
      "url": "https://myanimelist.net/anime/60058/Oshi_no_Ko_3rd_Season"
    },
    {
      "title": "Enen no Shouboutai: San no Shou Part 2",
      "image": "https://myanimelist.net/images/anime/1508/152472.jpg",
      "score": 8.05,
      "episodes": 13,
      "url": "https://myanimelist.net/anime/59229/Enen_no_Shouboutai__San_no_Shou_Part_2"
    }
  ],
  "latest_releases": [
    {
      "title": "[ToonsHub] Anyway Im Falling in Love with You S02E11 1080p CR WEB-DL AAC2.0 H.264 (Multi-Subs)",
      "link": "https://animetosho.org/view/toonshub-anyway-im-falling-love-s02e11-1080p-cr.k9792030617612",
      "magnet": "magnet:?xt=urn:btih:6DVUKRBSRTYRASDDFCAXC2DP34X5KHKP&tr=https%3A%2F%2Ftracker.nekobt.to%2Fapi%2Ftracker%2Fpublic%2Fannounce&tr=http%3A%2F%2Fnyaa.tracker.wf%3A7777%2Fannounce&tr=udp%3A%2F%2Ftracker.opentrackr.org%3A1337%2Fannounce&tr=udp%3A%2F%2Fexodus.desync.com%3A6969%2Fannounce&tr=udp%3A%2F%2Ftracker.torrent.eu.org%3A451%2Fannounce&dn=%5BToonsHub%5D%20Anyway%20Im%20Falling%20in%20Love%20with%20You%20S02E11%201080p%20CR%20WEB-DL%20AAC2.0%20H.264%20%28Multi-Subs%29",
      "hash": "6DVUKRBSRTYRASDDFCAXC2DP34X5KHKP",
      "nyaaUrl": "https://nyaa.si/?q=6DVUKRBSRTYRASDDFCAXC2DP34X5KHKP",
      "size": "NaN MB",
      "date": "20/3/2026, 00.01.59"
    },
    {
      "title": "[ToonsHub] Anyway Im Falling in Love with You S02E11 1080p BILI WEB-DL AAC2.0 H.265 (Multi-Subs)",
      "link": "https://animetosho.org/view/toonshub-anyway-im-falling-love-s02e11-1080p-bili.k9792014625803",
      "magnet": "magnet:?xt=urn:btih:JPVYCOUPPJLEVRRAUBQVE2MOLEUDEYN4&tr=https%3A%2F%2Ftracker.nekobt.to%2Fapi%2Ftracker%2Fpublic%2Fannounce&tr=http%3A%2F%2Fnyaa.tracker.wf%3A7777%2Fannounce&tr=udp%3A%2F%2Ftracker.opentrackr.org%3A1337%2Fannounce&tr=udp%3A%2F%2Fexodus.desync.com%3A6969%2Fannounce&tr=udp%3A%2F%2Ftracker.torrent.eu.org%3A451%2Fannounce&dn=%5BToonsHub%5D%20Anyway%20Im%20Falling%20in%20Love%20with%20You%20S02E11%201080p%20BILI%20WEB-DL%20AAC2.0%20H.265%20%28Multi-Subs%29",
      "hash": "JPVYCOUPPJLEVRRAUBQVE2MOLEUDEYN4",
      "nyaaUrl": "https://nyaa.si/?q=JPVYCOUPPJLEVRRAUBQVE2MOLEUDEYN4",
      "size": "NaN MB",
      "date": "20/3/2026, 00.00.57"
    },
    {
      "title": "JUJUTSU KAISEN S03E11 Tokyo Colony No 1-Part 5 1080p CR WEB-DL AAC2.0 H 264-VARYG (Jujutsu Kaisen: Shimetsu Kaiyuu - Zenpen, Multi-Subs)",
      "link": "https://animetosho.org/view/jujutsu-kaisen-s03e11-tokyo-colony-no-1-part.n2087994",
      "magnet": "magnet:?xt=urn:btih:RONTGZNMLSDPZCFTXEMNTKIEHSVXXUMI&tr=http%3A%2F%2Fnyaa.tracker.wf%3A7777%2Fannounce&tr=https%3A%2F%2Ftracker.nekobt.to%2Fapi%2Ftracker%2Fpublic%2Fannounce&tr=udp%3A%2F%2Fopen.stealth.si%3A80%2Fannounce&tr=udp%3A%2F%2Ftracker.opentrackr.org%3A1337%2Fannounce&tr=udp%3A%2F%2Fexodus.desync.com%3A6969%2Fannounce&dn=JUJUTSU%20KAISEN%20S03E11%20Tokyo%20Colony%20No%201-Part%205%201080p%20CR%20WEB-DL%20AAC2.0%20H%20264-VARYG%20%28Jujutsu%20Kaisen%3A%20Shimetsu%20Kaiyuu%20-%20Zenpen%2C%20Multi-Subs%29",
      "hash": "RONTGZNMLSDPZCFTXEMNTKIEHSVXXUMI",
      "nyaaUrl": "https://nyaa.si/?q=RONTGZNMLSDPZCFTXEMNTKIEHSVXXUMI",
      "size": "NaN MB",
      "date": "19/3/2026, 23.57.43"
    },
    {
      "title": "[Raze] Yuusha-kei ni Shosu - 11 (Dual-Audio) x265 10bit 1080p 143.8561fps.mkv",
      "link": "https://animetosho.org/view/raze-yuusha-kei-ni-shosu-11-dual-audio.n2087992",
      "magnet": "magnet:?xt=urn:btih:TR4GQWDDHRJXAUGUEY3Z3QOC7VTN5TVS&tr=http%3A%2F%2Fnyaa.tracker.wf%3A7777%2Fannounce&tr=udp%3A%2F%2Fopen.stealth.si%3A80%2Fannounce&tr=udp%3A%2F%2Ftracker.opentrackr.org%3A1337%2Fannounce&tr=udp%3A%2F%2Fexodus.desync.com%3A6969%2Fannounce&tr=udp%3A%2F%2Ftracker.torrent.eu.org%3A451%2Fannounce&dn=%5BRaze%5D%20Yuusha-kei%20ni%20Shosu%20-%2011%20%28Dual-Audio%29%20x265%2010bit%201080p%20143.8561fps.mkv",
      "hash": "TR4GQWDDHRJXAUGUEY3Z3QOC7VTN5TVS",
      "nyaaUrl": "https://nyaa.si/?q=TR4GQWDDHRJXAUGUEY3Z3QOC7VTN5TVS",
      "size": "NaN MB",
      "date": "19/3/2026, 23.49.55"
    },
    {
      "title": "[SubsPlease] Jujutsu Kaisen - 58 (1080p) [3D64E486].mkv",
      "link": "https://animetosho.org/view/subsplease-jujutsu-kaisen-58-1080p-3d64e486-mkv.n2087990",
      "magnet": "magnet:?xt=urn:btih:2GZQP44IYZFFYC3JDYJN52OXCPW2MVGT&tr=http%3A%2F%2Fnyaa.tracker.wf%3A7777%2Fannounce&tr=udp%3A%2F%2Ftracker.opentrackr.org%3A1337%2Fannounce&tr=udp%3A%2F%2Fopen.stealth.si%3A80%2Fannounce&tr=udp%3A%2F%2Fexodus.desync.com%3A6969%2Fannounce&tr=udp%3A%2F%2Ftracker.torrent.eu.org%3A451%2Fannounce&dn=%5BSubsPlease%5D%20Jujutsu%20Kaisen%20-%2058%20%281080p%29%20%5B3D64E486%5D.mkv",
      "hash": "2GZQP44IYZFFYC3JDYJN52OXCPW2MVGT",
      "nyaaUrl": "https://nyaa.si/?q=2GZQP44IYZFFYC3JDYJN52OXCPW2MVGT",
      "size": "NaN MB",
      "date": "19/3/2026, 23.45.25"
    },
    {
      "title": "[SubsPlease] Jujutsu Kaisen - 58 (720p) [844324D5].mkv",
      "link": "https://animetosho.org/view/subsplease-jujutsu-kaisen-58-720p-844324d5-mkv.n2087989",
      "magnet": "magnet:?xt=urn:btih:RWWE6KUSUOZRA5PB6TE37RPB3UBZMHUN&tr=http%3A%2F%2Fnyaa.tracker.wf%3A7777%2Fannounce&tr=udp%3A%2F%2Ftracker.opentrackr.org%3A1337%2Fannounce&tr=udp%3A%2F%2Fopen.stealth.si%3A80%2Fannounce&tr=udp%3A%2F%2Fexodus.desync.com%3A6969%2Fannounce&tr=udp%3A%2F%2Ftracker.torrent.eu.org%3A451%2Fannounce&dn=%5BSubsPlease%5D%20Jujutsu%20Kaisen%20-%2058%20%28720p%29%20%5B844324D5%5D.mkv",
      "hash": "RWWE6KUSUOZRA5PB6TE37RPB3UBZMHUN",
      "nyaaUrl": "https://nyaa.si/?q=RWWE6KUSUOZRA5PB6TE37RPB3UBZMHUN",
      "size": "NaN MB",
      "date": "19/3/2026, 23.45.20"
    },
    {
      "title": "[SubsPlease] Jujutsu Kaisen - 58 (480p) [B904F5B4].mkv",
      "link": "https://animetosho.org/view/subsplease-jujutsu-kaisen-58-480p-b904f5b4-mkv.n2087988",
      "magnet": "magnet:?xt=urn:btih:O6JEGB6UGU3HFG55HO4LMPYOL62QL2WK&tr=http%3A%2F%2Fnyaa.tracker.wf%3A7777%2Fannounce&tr=udp%3A%2F%2Ftracker.opentrackr.org%3A1337%2Fannounce&tr=udp%3A%2F%2Fopen.stealth.si%3A80%2Fannounce&tr=udp%3A%2F%2Fexodus.desync.com%3A6969%2Fannounce&tr=udp%3A%2F%2Ftracker.torrent.eu.org%3A451%2Fannounce&dn=%5BSubsPlease%5D%20Jujutsu%20Kaisen%20-%2058%20%28480p%29%20%5BB904F5B4%5D.mkv",
      "hash": "O6JEGB6UGU3HFG55HO4LMPYOL62QL2WK",
      "nyaaUrl": "https://nyaa.si/?q=O6JEGB6UGU3HFG55HO4LMPYOL62QL2WK",
      "size": "NaN MB",
      "date": "19/3/2026, 23.45.19"
    },
    {
      "title": "[ToonsHub] Jujutsu Kaisen S03E11 1080p AMZN WEB-DL DDP2.0 H.264 (English-Sub)",
      "link": "https://animetosho.org/view/toonshub-jujutsu-kaisen-s03e11-1080p-amzn-web-dl.k9791738349058",
      "magnet": "magnet:?xt=urn:btih:2AYFML47A5V3Z7KONGZEVUTCGXNYG4GY&tr=https%3A%2F%2Ftracker.nekobt.to%2Fapi%2Ftracker%2Fpublic%2Fannounce&tr=http%3A%2F%2Fnyaa.tracker.wf%3A7777%2Fannounce&tr=udp%3A%2F%2Ftracker.opentrackr.org%3A1337%2Fannounce&tr=udp%3A%2F%2Fexodus.desync.com%3A6969%2Fannounce&tr=udp%3A%2F%2Ftracker.torrent.eu.org%3A451%2Fannounce&dn=%5BToonsHub%5D%20Jujutsu%20Kaisen%20S03E11%201080p%20AMZN%20WEB-DL%20DDP2.0%20H.264%20%28English-Sub%29",
      "hash": "2AYFML47A5V3Z7KONGZEVUTCGXNYG4GY",
      "nyaaUrl": "https://nyaa.si/?q=2AYFML47A5V3Z7KONGZEVUTCGXNYG4GY",
      "size": "NaN MB",
      "date": "19/3/2026, 23.42.57"
    },
    {
      "title": "[Onalrie] Toumei Otoko to Ningen Onna - S01E11 [1080p WEBRip AV1].mkv",
      "link": "https://animetosho.org/view/onalrie-toumei-otoko-ningen-onna-s01e11-1080p-webrip-av1-mkv.2068075",
      "magnet": "magnet:?xt=urn:btih:WJQNNEXKLH7HVOK3IDRJB2FWLXO27B4N&tr=http%3A%2F%2Ftracker.onalrie.app%3A7070%2Fannounce&tr=udp%3A%2F%2Ftracker.onalrie.app%3A6969%2Fannounce&tr=http%3A%2F%2Ftracker.beeimg.com%3A6969%2Fannounce&tr=http%3A%2F%2Ftracker.mywaifu.best%3A6969%2Fannounce&tr=https%3A%2F%2Ftracker.zhuqiy.com%3A443%2Fannounce&dn=%5BOnalrie%5D%20Toumei%20Otoko%20to%20Ningen%20Onna%20-%20S01E11%20%5B1080p%20WEBRip%20AV1%5D.mkv",
      "hash": "WJQNNEXKLH7HVOK3IDRJB2FWLXO27B4N",
      "nyaaUrl": "https://nyaa.si/?q=WJQNNEXKLH7HVOK3IDRJB2FWLXO27B4N",
      "size": "NaN MB",
      "date": "19/3/2026, 23.40.00"
    },
    {
      "title": "[ToonsHub] JUJUTSU KAISEN S03E11 1080p CR WEB-DL AAC2.0 H.264 (Multi-Subs)",
      "link": "https://animetosho.org/view/toonshub-jujutsu-kaisen-s03e11-1080p-cr-web-dl.k9791568969729",
      "magnet": "magnet:?xt=urn:btih:OR5N3FDUGPLYMTJ7REWAE7Q3OI5C5HPY&tr=https%3A%2F%2Ftracker.nekobt.to%2Fapi%2Ftracker%2Fpublic%2Fannounce&tr=http%3A%2F%2Fnyaa.tracker.wf%3A7777%2Fannounce&tr=udp%3A%2F%2Ftracker.opentrackr.org%3A1337%2Fannounce&tr=udp%3A%2F%2Fexodus.desync.com%3A6969%2Fannounce&tr=udp%3A%2F%2Ftracker.torrent.eu.org%3A451%2Fannounce&dn=%5BToonsHub%5D%20JUJUTSU%20KAISEN%20S03E11%201080p%20CR%20WEB-DL%20AAC2.0%20H.264%20%28Multi-Subs%29",
      "hash": "OR5N3FDUGPLYMTJ7REWAE7Q3OI5C5HPY",
      "nyaaUrl": "https://nyaa.si/?q=OR5N3FDUGPLYMTJ7REWAE7Q3OI5C5HPY",
      "size": "NaN MB",
      "date": "19/3/2026, 23.31.56"
    }
  ]
}