{
  "last_update": "25/3/2026, 22.05.43 WIB",
  "ongoing_anime": [
    {
      "title": "Sousou no Frieren 2nd Season",
      "image": "https://myanimelist.net/images/anime/1921/154528.jpg",
      "score": 9,
      "episodes": 10,
      "url": "https://myanimelist.net/anime/59978/Sousou_no_Frieren_2nd_Season"
    },
    {
      "title": "Jujutsu Kaisen: Shimetsu Kaiyuu - Zenpen",
      "image": "https://myanimelist.net/images/anime/1659/154920.jpg",
      "score": 8.58,
      "episodes": 12,
      "url": "https://myanimelist.net/anime/57658/Jujutsu_Kaisen__Shimetsu_Kaiyuu_-_Zenpen"
    },
    {
      "title": "Jigokuraku 2nd Season",
      "image": "https://myanimelist.net/images/anime/1772/154456.jpg",
      "score": 8.25,
      "episodes": 12,
      "url": "https://myanimelist.net/anime/55825/Jigokuraku_2nd_Season"
    },
    {
      "title": "Yuusha-kei ni Shosu: Choubatsu Yuusha 9004-tai Keimu Kiroku",
      "image": "https://myanimelist.net/images/anime/1062/151911.jpg",
      "score": 8.12,
      "episodes": 12,
      "url": "https://myanimelist.net/anime/56009/Yuusha-kei_ni_Shosu__Choubatsu_Yuusha_9004-tai_Keimu_Kiroku"
    },
    {
      "title": "[Oshi no Ko] 3rd Season",
      "image": "https://myanimelist.net/images/anime/1979/153329.jpg",
      "score": 8.6,
      "episodes": 11,
      "url": "https://myanimelist.net/anime/60058/Oshi_no_Ko_3rd_Season"
    },
    {
      "title": "Steel Ball Run: JoJo no Kimyou na Bouken",
      "image": "https://myanimelist.net/images/anime/1448/154111.jpg",
      "score": 9.21,
      "episodes": null,
      "url": "https://myanimelist.net/anime/61469/Steel_Ball_Run__JoJo_no_Kimyou_na_Bouken"
    }
  ],
  "latest_releases": [
    {
      "title": "[Polarwindz] The Summer Hikaru Died (Hikaru ga Shinda Natsu) (BD 1080p HEVC Opus Dual Audio)",
      "link": "https://animetosho.org/view/polarwindz-summer-hikaru-died-ga-shinda-natsu-bd.n2090068",
      "magnet": "magnet:?xt=urn:btih:6X4XQGHKNAHCJHSKM44UA7T46MBVO55Z&tr=http%3A%2F%2Fnyaa.tracker.wf%3A7777%2Fannounce&tr=udp%3A%2F%2Fopen.stealth.si%3A80%2Fannounce&tr=udp%3A%2F%2Ftracker.opentrackr.org%3A1337%2Fannounce&tr=udp%3A%2F%2Fexodus.desync.com%3A6969%2Fannounce&tr=udp%3A%2F%2Ftracker.torrent.eu.org%3A451%2Fannounce&dn=%5BPolarwindz%5D%20The%20Summer%20Hikaru%20Died%20%28Hikaru%20ga%20Shinda%20Natsu%29%20%28BD%201080p%20HEVC%20Opus%20Dual%20Audio%29",
      "hash": "6X4XQGHKNAHCJHSKM44UA7T46MBVO55Z",
      "nyaaUrl": "https://nyaa.si/?q=6X4XQGHKNAHCJHSKM44UA7T46MBVO55Z",
      "size": "NaN MB",
      "date": "25/3/2026, 21.50.30"
    },
    {
      "title": "[FSP] Douluo Dalu II - Soul Land 2 - 145 [1080p]",
      "link": "https://animetosho.org/view/fsp-douluo-dalu-ii-soul-land-2-145-1080p.n2090066",
      "magnet": "magnet:?xt=urn:btih:BRUPTAHGRJG2I4COPCTMIJICGHRANTS5&tr=http%3A%2F%2Fnyaa.tracker.wf%3A7777%2Fannounce&tr=udp%3A%2F%2Fopen.stealth.si%3A80%2Fannounce&tr=udp%3A%2F%2Ftracker.opentrackr.org%3A1337%2Fannounce&tr=udp%3A%2F%2Fexodus.desync.com%3A6969%2Fannounce&tr=udp%3A%2F%2Ftracker.torrent.eu.org%3A451%2Fannounce&dn=%5BFSP%5D%20Douluo%20Dalu%20II%20-%20Soul%20Land%202%20-%20145%20%5B1080p%5D",
      "hash": "BRUPTAHGRJG2I4COPCTMIJICGHRANTS5",
      "nyaaUrl": "https://nyaa.si/?q=BRUPTAHGRJG2I4COPCTMIJICGHRANTS5",
      "size": "NaN MB",
      "date": "25/3/2026, 21.39.29"
    },
    {
      "title": "[FSP DN] The Gate of Mystical Realm - 20 (4K) | 玄界之门",
      "link": "https://animetosho.org/view/fsp-dn-gate-mystical-realm-20-4k.n2090065",
      "magnet": "magnet:?xt=urn:btih:NKEGOP3OD2FPHK3NT4L3G6FNVNM3L7FL&tr=http%3A%2F%2Fnyaa.tracker.wf%3A7777%2Fannounce&tr=udp%3A%2F%2Fopen.stealth.si%3A80%2Fannounce&tr=udp%3A%2F%2Ftracker.opentrackr.org%3A1337%2Fannounce&tr=udp%3A%2F%2Fexodus.desync.com%3A6969%2Fannounce&tr=udp%3A%2F%2Ftracker.torrent.eu.org%3A451%2Fannounce&dn=%5BFSP%20DN%5D%20The%20Gate%20of%20Mystical%20Realm%20-%2020%20%284K%29%20%7C%20%E7%8E%84%E7%95%8C%E4%B9%8B%E9%97%A8",
      "hash": "NKEGOP3OD2FPHK3NT4L3G6FNVNM3L7FL",
      "nyaaUrl": "https://nyaa.si/?q=NKEGOP3OD2FPHK3NT4L3G6FNVNM3L7FL",
      "size": "NaN MB",
      "date": "25/3/2026, 21.39.26"
    },
    {
      "title": "[ASW] Okiraku Ryoushu no Tanoshii Ryouchi Bouei - 12 [1080p HEVC x265 10Bit][AAC]",
      "link": "https://animetosho.org/view/asw-okiraku-ryoushu-no-tanoshii-ryouchi-bouei-12.n2090062",
      "magnet": "magnet:?xt=urn:btih:VGVACYXL2WH5NUTYZPKQOI7QKE7U7GT4&tr=http%3A%2F%2Fnyaa.tracker.wf%3A7777%2Fannounce&tr=udp%3A%2F%2Fopen.stealth.si%3A80%2Fannounce&tr=udp%3A%2F%2Ftracker.opentrackr.org%3A1337%2Fannounce&tr=udp%3A%2F%2Fexodus.desync.com%3A6969%2Fannounce&tr=udp%3A%2F%2Ftracker.torrent.eu.org%3A451%2Fannounce&dn=%5BASW%5D%20Okiraku%20Ryoushu%20no%20Tanoshii%20Ryouchi%20Bouei%20-%2012%20%5B1080p%20HEVC%20x265%2010Bit%5D%5BAAC%5D",
      "hash": "VGVACYXL2WH5NUTYZPKQOI7QKE7U7GT4",
      "nyaaUrl": "https://nyaa.si/?q=VGVACYXL2WH5NUTYZPKQOI7QKE7U7GT4",
      "size": "NaN MB",
      "date": "25/3/2026, 21.33.16"
    },
    {
      "title": "[New-raws] Okiraku Ryoushu no Tanoshii Ryouchi Bouei - 01~12 [1080p] [Bstation].mkv",
      "link": "https://animetosho.org/view/new-raws-okiraku-ryoushu-no-tanoshii-ryouchi-bouei.n2090057",
      "magnet": "magnet:?xt=urn:btih:LC3F7FVGYLVSJTSGRFLE64JKPBPMYKIX&tr=http%3A%2F%2Fnyaa.tracker.wf%3A7777%2Fannounce&tr=udp%3A%2F%2Fexodus.desync.com%3A6969%2Fannounce&tr=udp%3A%2F%2Ftracker.tiny-vps.com%3A6969%2Fannounce&tr=udp%3A%2F%2Ftracker.opentrackr.org%3A1337%2Fannounce&tr=udp%3A%2F%2Ftracker.torrent.eu.org%3A451%2Fannounce&dn=%5BNew-raws%5D%20Okiraku%20Ryoushu%20no%20Tanoshii%20Ryouchi%20Bouei%20-%2001~12%20%5B1080p%5D%20%5BBstation%5D.mkv",
      "hash": "LC3F7FVGYLVSJTSGRFLE64JKPBPMYKIX",
      "nyaaUrl": "https://nyaa.si/?q=LC3F7FVGYLVSJTSGRFLE64JKPBPMYKIX",
      "size": "NaN MB",
      "date": "25/3/2026, 21.30.35"
    },
    {
      "title": "[Judas] 29-sai Dokushin Chuuken Boukensha no Nichijou (An Adventurer’s Daily Grind at Age 29) - S01E11 [1080p][HEVC x265 10bit][Multi-Subs] (Weekly)",
      "link": "https://animetosho.org/view/judas-29-sai-dokushin-chuuken-boukensha-no-nichijou.n2090056",
      "magnet": "magnet:?xt=urn:btih:4X2O5QCZ76SYXZSGWVZLRTWAFQR477LR&tr=http%3A%2F%2Fnyaa.tracker.wf%3A7777%2Fannounce&tr=udp%3A%2F%2Fopen.stealth.si%3A80%2Fannounce&tr=udp%3A%2F%2Ftracker.opentrackr.org%3A1337%2Fannounce&tr=udp%3A%2F%2Fexodus.desync.com%3A6969%2Fannounce&tr=udp%3A%2F%2Ftracker.torrent.eu.org%3A451%2Fannounce&dn=%5BJudas%5D%2029-sai%20Dokushin%20Chuuken%20Boukensha%20no%20Nichijou%20%28An%20Adventurer%E2%80%99s%20Daily%20Grind%20at%20Age%2029%29%20-%20S01E11%20%5B1080p%5D%5BHEVC%20x265%2010bit%5D%5BMulti-Subs%5D%20%28Weekly%29",
      "hash": "4X2O5QCZ76SYXZSGWVZLRTWAFQR477LR",
      "nyaaUrl": "https://nyaa.si/?q=4X2O5QCZ76SYXZSGWVZLRTWAFQR477LR",
      "size": "NaN MB",
      "date": "25/3/2026, 21.26.03"
    },
    {
      "title": "[Onalrie] 29-sai Dokushin Chuuken Boukensha no Nichijou - S01E12 [1080p WEBRip AV1].mkv",
      "link": "https://animetosho.org/view/onalrie-29-sai-dokushin-chuuken-boukensha-no-nichijou.2069429",
      "magnet": "magnet:?xt=urn:btih:I3QXNW4TRWTGZB5B5NKIPAXXLQ2RNMRT&tr=http%3A%2F%2Ftracker.onalrie.app%3A7070%2Fannounce&tr=udp%3A%2F%2Ftracker.onalrie.app%3A6969%2Fannounce&tr=http%3A%2F%2Ftracker.beeimg.com%3A6969%2Fannounce&tr=http%3A%2F%2Ftracker.mywaifu.best%3A6969%2Fannounce&tr=https%3A%2F%2Ftracker.zhuqiy.com%3A443%2Fannounce&dn=%5BOnalrie%5D%2029-sai%20Dokushin%20Chuuken%20Boukensha%20no%20Nichijou%20-%20S01E12%20%5B1080p%20WEBRip%20AV1%5D.mkv",
      "hash": "I3QXNW4TRWTGZB5B5NKIPAXXLQ2RNMRT",
      "nyaaUrl": "https://nyaa.si/?q=I3QXNW4TRWTGZB5B5NKIPAXXLQ2RNMRT",
      "size": "NaN MB",
      "date": "25/3/2026, 21.18.00"
    },
    {
      "title": "[jaaj] Vinland Saga S01 (2019) (BD 1080p AV1 AAC)",
      "link": "https://animetosho.org/view/jaaj-vinland-saga-s01-2019-bd-1080p-av1-aac.k9922001122310",
      "magnet": "magnet:?xt=urn:btih:S5A7KAFWIQ7THYAI4MODLIHGSC76HZ56&tr=https%3A%2F%2Ftracker.nekobt.to%2Fapi%2Ftracker%2Fpublic%2Fannounce&tr=udp%3A%2F%2Fopen.stealth.si%3A80%2Fannounce&tr=udp%3A%2F%2Fexodus.desync.com%3A6969%2Fannounce&tr=udp%3A%2F%2Ftracker.opentrackr.org%3A1337%2Fannounce&tr=udp%3A%2F%2Ftracker.qu.ax%3A6969%2Fannounce&dn=%5Bjaaj%5D%20Vinland%20Saga%20S01%20%282019%29%20%28BD%201080p%20AV1%20AAC%29",
      "hash": "S5A7KAFWIQ7THYAI4MODLIHGSC76HZ56",
      "nyaaUrl": "https://nyaa.si/?q=S5A7KAFWIQ7THYAI4MODLIHGSC76HZ56",
      "size": "NaN MB",
      "date": "25/3/2026, 21.03.36"
    },
    {
      "title": "[shincaps] Arne no Jikenbo - 12 (ANIPLUS 1920x1080 H264 AAC).ts",
      "link": "https://animetosho.org/view/shincaps-arne-no-jikenbo-12-aniplus-1920x1080-h264-aac-ts.n2090049",
      "magnet": "magnet:?xt=urn:btih:YNUSZ7DOVRTKJCXT4OI6M54YKYV3URCE&tr=http%3A%2F%2Fnyaa.tracker.wf%3A7777%2Fannounce&tr=udp%3A%2F%2Fopen.stealth.si%3A80%2Fannounce&tr=udp%3A%2F%2Ftracker.opentrackr.org%3A1337%2Fannounce&tr=udp%3A%2F%2Fexodus.desync.com%3A6969%2Fannounce&tr=udp%3A%2F%2Ftracker.torrent.eu.org%3A451%2Fannounce&dn=%5Bshincaps%5D%20Arne%20no%20Jikenbo%20-%2012%20%28ANIPLUS%201920x1080%20H264%20AAC%29.ts",
      "hash": "YNUSZ7DOVRTKJCXT4OI6M54YKYV3URCE",
      "nyaaUrl": "https://nyaa.si/?q=YNUSZ7DOVRTKJCXT4OI6M54YKYV3URCE",
      "size": "NaN MB",
      "date": "25/3/2026, 21.00.58"
    },
    {
      "title": "[Onalrie] Okiraku Ryoushu no Tanoshii Ryouchi Bouei - S01E12 [1080p WEBRip AV1].mkv",
      "link": "https://animetosho.org/view/onalrie-okiraku-ryoushu-no-tanoshii-ryouchi-bouei-s01e12.2069424",
      "magnet": "magnet:?xt=urn:btih:CIJEEF4FS42NPKOJAJ5SFTT7J4BWB4SZ&tr=http%3A%2F%2Ftracker.onalrie.app%3A7070%2Fannounce&tr=udp%3A%2F%2Ftracker.onalrie.app%3A6969%2Fannounce&tr=http%3A%2F%2Ftracker.beeimg.com%3A6969%2Fannounce&tr=http%3A%2F%2Ftracker.mywaifu.best%3A6969%2Fannounce&tr=https%3A%2F%2Ftracker.zhuqiy.com%3A443%2Fannounce&dn=%5BOnalrie%5D%20Okiraku%20Ryoushu%20no%20Tanoshii%20Ryouchi%20Bouei%20-%20S01E12%20%5B1080p%20WEBRip%20AV1%5D.mkv",
      "hash": "CIJEEF4FS42NPKOJAJ5SFTT7J4BWB4SZ",
      "nyaaUrl": "https://nyaa.si/?q=CIJEEF4FS42NPKOJAJ5SFTT7J4BWB4SZ",
      "size": "NaN MB",
      "date": "25/3/2026, 20.51.00"
    }
  ]
}