{
  "last_update": "21/3/2026, 22.31.47 WIB",
  "ongoing_anime": [
    {
      "title": "Sousou no Frieren 2nd Season",
      "image": "https://myanimelist.net/images/anime/1921/154528.jpg",
      "score": 9.11,
      "episodes": 10,
      "url": "https://myanimelist.net/anime/59978/Sousou_no_Frieren_2nd_Season"
    },
    {
      "title": "Jujutsu Kaisen: Shimetsu Kaiyuu - Zenpen",
      "image": "https://myanimelist.net/images/anime/1659/154920.jpg",
      "score": 8.58,
      "episodes": 12,
      "url": "https://myanimelist.net/anime/57658/Jujutsu_Kaisen__Shimetsu_Kaiyuu_-_Zenpen"
    },
    {
      "title": "Jigokuraku 2nd Season",
      "image": "https://myanimelist.net/images/anime/1772/154456.jpg",
      "score": 8.24,
      "episodes": 12,
      "url": "https://myanimelist.net/anime/55825/Jigokuraku_2nd_Season"
    },
    {
      "title": "Yuusha-kei ni Shosu: Choubatsu Yuusha 9004-tai Keimu Kiroku",
      "image": "https://myanimelist.net/images/anime/1062/151911.jpg",
      "score": 8.14,
      "episodes": 12,
      "url": "https://myanimelist.net/anime/56009/Yuusha-kei_ni_Shosu__Choubatsu_Yuusha_9004-tai_Keimu_Kiroku"
    },
    {
      "title": "[Oshi no Ko] 3rd Season",
      "image": "https://myanimelist.net/images/anime/1979/153329.jpg",
      "score": 8.6,
      "episodes": 11,
      "url": "https://myanimelist.net/anime/60058/Oshi_no_Ko_3rd_Season"
    },
    {
      "title": "Enen no Shouboutai: San no Shou Part 2",
      "image": "https://myanimelist.net/images/anime/1508/152472.jpg",
      "score": 8.06,
      "episodes": 13,
      "url": "https://myanimelist.net/anime/59229/Enen_no_Shouboutai__San_no_Shou_Part_2"
    }
  ],
  "latest_releases": [
    {
      "title": "[ToonsHub] TRIGUN STARGAZE S02E11 1080p CR WEB-DL AAC2.0 H.264 (Multi-Subs)",
      "link": "https://animetosho.org/view/toonshub-trigun-stargaze-s02e11-1080p-cr-web-dl.k9834534386178",
      "magnet": "magnet:?xt=urn:btih:PORS2CSSPWBRL5YJD56RHAWEFY4XJYPG&tr=https%3A%2F%2Ftracker.nekobt.to%2Fapi%2Ftracker%2Fpublic%2Fannounce&tr=http%3A%2F%2Fnyaa.tracker.wf%3A7777%2Fannounce&tr=udp%3A%2F%2Ftracker.opentrackr.org%3A1337%2Fannounce&tr=udp%3A%2F%2Fexodus.desync.com%3A6969%2Fannounce&tr=udp%3A%2F%2Ftracker.torrent.eu.org%3A451%2Fannounce&dn=%5BToonsHub%5D%20TRIGUN%20STARGAZE%20S02E11%201080p%20CR%20WEB-DL%20AAC2.0%20H.264%20%28Multi-Subs%29",
      "hash": "PORS2CSSPWBRL5YJD56RHAWEFY4XJYPG",
      "nyaaUrl": "https://nyaa.si/?q=PORS2CSSPWBRL5YJD56RHAWEFY4XJYPG",
      "size": "NaN MB",
      "date": "21/3/2026, 22.09.09"
    },
    {
      "title": "[Erai-raws] Trigun Stargaze - 11 [480p CR WEB-DL AVC AAC][MultiSub][C8E778A0]",
      "link": "https://animetosho.org/view/erai-raws-trigun-stargaze-11-480p-cr-web.n2088708",
      "magnet": "magnet:?xt=urn:btih:L52P4UQ72A5UEPAUFBKTF5X4YOHIIDQB&tr=http%3A%2F%2Fnyaa.tracker.wf%3A7777%2Fannounce&tr=udp%3A%2F%2Fopen.stealth.si%3A80%2Fannounce&tr=udp%3A%2F%2Ftracker.opentrackr.org%3A1337%2Fannounce&tr=udp%3A%2F%2Ftracker.torrent.eu.org%3A451%2Fannounce&tr=udp%3A%2F%2Ftracker.tiny-vps.com%3A6969%2Fannounce&dn=%5BErai-raws%5D%20Trigun%20Stargaze%20-%2011%20%5B480p%20CR%20WEB-DL%20AVC%20AAC%5D%5BMultiSub%5D%5BC8E778A0%5D",
      "hash": "L52P4UQ72A5UEPAUFBKTF5X4YOHIIDQB",
      "nyaaUrl": "https://nyaa.si/?q=L52P4UQ72A5UEPAUFBKTF5X4YOHIIDQB",
      "size": "NaN MB",
      "date": "21/3/2026, 22.05.22"
    },
    {
      "title": "[Erai-raws] Trigun Stargaze - 11 [720p CR WEB-DL AVC AAC][MultiSub][303F521D]",
      "link": "https://animetosho.org/view/erai-raws-trigun-stargaze-11-720p-cr-web.n2088707",
      "magnet": "magnet:?xt=urn:btih:WLKYQ74D573EV4VNDUJATXNMWLGCBNMA&tr=http%3A%2F%2Fnyaa.tracker.wf%3A7777%2Fannounce&tr=udp%3A%2F%2Fopen.stealth.si%3A80%2Fannounce&tr=udp%3A%2F%2Ftracker.opentrackr.org%3A1337%2Fannounce&tr=udp%3A%2F%2Ftracker.torrent.eu.org%3A451%2Fannounce&tr=udp%3A%2F%2Ftracker.tiny-vps.com%3A6969%2Fannounce&dn=%5BErai-raws%5D%20Trigun%20Stargaze%20-%2011%20%5B720p%20CR%20WEB-DL%20AVC%20AAC%5D%5BMultiSub%5D%5B303F521D%5D",
      "hash": "WLKYQ74D573EV4VNDUJATXNMWLGCBNMA",
      "nyaaUrl": "https://nyaa.si/?q=WLKYQ74D573EV4VNDUJATXNMWLGCBNMA",
      "size": "NaN MB",
      "date": "21/3/2026, 22.05.11"
    },
    {
      "title": "[Judas] Jingai Kyoushitsu no Ningengirai Kyoushi (A Misanthrope Teaches a Class for Demi-Humans) - S01E10 [1080p][HEVC x265 10bit][Multi-Subs] (Weekly)",
      "link": "https://animetosho.org/view/judas-jingai-kyoushitsu-no-ningengirai-kyoushi-misanthrope.n2088706",
      "magnet": "magnet:?xt=urn:btih:K6DAAZR32BKCSBJKQTOUCM2FP7IVVVEV&tr=http%3A%2F%2Fnyaa.tracker.wf%3A7777%2Fannounce&tr=udp%3A%2F%2Fopen.stealth.si%3A80%2Fannounce&tr=udp%3A%2F%2Ftracker.opentrackr.org%3A1337%2Fannounce&tr=udp%3A%2F%2Fexodus.desync.com%3A6969%2Fannounce&tr=udp%3A%2F%2Ftracker.torrent.eu.org%3A451%2Fannounce&dn=%5BJudas%5D%20Jingai%20Kyoushitsu%20no%20Ningengirai%20Kyoushi%20%28A%20Misanthrope%20Teaches%20a%20Class%20for%20Demi-Humans%29%20-%20S01E10%20%5B1080p%5D%5BHEVC%20x265%2010bit%5D%5BMulti-Subs%5D%20%28Weekly%29",
      "hash": "K6DAAZR32BKCSBJKQTOUCM2FP7IVVVEV",
      "nyaaUrl": "https://nyaa.si/?q=K6DAAZR32BKCSBJKQTOUCM2FP7IVVVEV",
      "size": "NaN MB",
      "date": "21/3/2026, 22.05.01"
    },
    {
      "title": "[SubsPlease] Trigun Stargaze - 23 (1080p) [04451004].mkv",
      "link": "https://animetosho.org/view/subsplease-trigun-stargaze-23-1080p-04451004-mkv.n2088705",
      "magnet": "magnet:?xt=urn:btih:HIESFAPEBVVAKZHMOODGZOQ6EKTLZ7RU&tr=http%3A%2F%2Fnyaa.tracker.wf%3A7777%2Fannounce&tr=udp%3A%2F%2Ftracker.opentrackr.org%3A1337%2Fannounce&tr=udp%3A%2F%2Fopen.stealth.si%3A80%2Fannounce&tr=udp%3A%2F%2Fexodus.desync.com%3A6969%2Fannounce&tr=udp%3A%2F%2Ftracker.torrent.eu.org%3A451%2Fannounce&dn=%5BSubsPlease%5D%20Trigun%20Stargaze%20-%2023%20%281080p%29%20%5B04451004%5D.mkv",
      "hash": "HIESFAPEBVVAKZHMOODGZOQ6EKTLZ7RU",
      "nyaaUrl": "https://nyaa.si/?q=HIESFAPEBVVAKZHMOODGZOQ6EKTLZ7RU",
      "size": "NaN MB",
      "date": "21/3/2026, 22.04.19"
    },
    {
      "title": "[SubsPlease] Dead Account - 11 (1080p) [F662009C].mkv",
      "link": "https://animetosho.org/view/subsplease-dead-account-11-1080p-f662009c-mkv.n2088704",
      "magnet": "magnet:?xt=urn:btih:QDX6ZWCWVM7FVEZL5VLHKDNNEEXWSHWO&tr=http%3A%2F%2Fnyaa.tracker.wf%3A7777%2Fannounce&tr=udp%3A%2F%2Ftracker.opentrackr.org%3A1337%2Fannounce&tr=udp%3A%2F%2Fopen.stealth.si%3A80%2Fannounce&tr=udp%3A%2F%2Fexodus.desync.com%3A6969%2Fannounce&tr=udp%3A%2F%2Ftracker.torrent.eu.org%3A451%2Fannounce&dn=%5BSubsPlease%5D%20Dead%20Account%20-%2011%20%281080p%29%20%5BF662009C%5D.mkv",
      "hash": "QDX6ZWCWVM7FVEZL5VLHKDNNEEXWSHWO",
      "nyaaUrl": "https://nyaa.si/?q=QDX6ZWCWVM7FVEZL5VLHKDNNEEXWSHWO",
      "size": "NaN MB",
      "date": "21/3/2026, 22.03.50"
    },
    {
      "title": "[New-raws] Dead Account - 11 [1080p] [Bstation].mkv",
      "link": "https://animetosho.org/view/new-raws-dead-account-11-1080p-bstation-mkv.n2088703",
      "magnet": "magnet:?xt=urn:btih:6S6ZS5PPPRMO47RFNLCEJZ7PY7OSPDRD&tr=http%3A%2F%2Fnyaa.tracker.wf%3A7777%2Fannounce&tr=udp%3A%2F%2Fexodus.desync.com%3A6969%2Fannounce&tr=udp%3A%2F%2Ftracker.tiny-vps.com%3A6969%2Fannounce&tr=udp%3A%2F%2Ftracker.opentrackr.org%3A1337%2Fannounce&tr=udp%3A%2F%2Ftracker.torrent.eu.org%3A451%2Fannounce&dn=%5BNew-raws%5D%20Dead%20Account%20-%2011%20%5B1080p%5D%20%5BBstation%5D.mkv",
      "hash": "6S6ZS5PPPRMO47RFNLCEJZ7PY7OSPDRD",
      "nyaaUrl": "https://nyaa.si/?q=6S6ZS5PPPRMO47RFNLCEJZ7PY7OSPDRD",
      "size": "NaN MB",
      "date": "21/3/2026, 22.03.40"
    },
    {
      "title": "[SubsPlease] Trigun Stargaze - 23 (720p) [7A14457A].mkv",
      "link": "https://animetosho.org/view/subsplease-trigun-stargaze-23-720p-7a14457a-mkv.n2088702",
      "magnet": "magnet:?xt=urn:btih:MSPD7UDLWMYO2IXTOE3WIKGHHPQUB7TT&tr=http%3A%2F%2Fnyaa.tracker.wf%3A7777%2Fannounce&tr=udp%3A%2F%2Ftracker.opentrackr.org%3A1337%2Fannounce&tr=udp%3A%2F%2Fopen.stealth.si%3A80%2Fannounce&tr=udp%3A%2F%2Fexodus.desync.com%3A6969%2Fannounce&tr=udp%3A%2F%2Ftracker.torrent.eu.org%3A451%2Fannounce&dn=%5BSubsPlease%5D%20Trigun%20Stargaze%20-%2023%20%28720p%29%20%5B7A14457A%5D.mkv",
      "hash": "MSPD7UDLWMYO2IXTOE3WIKGHHPQUB7TT",
      "nyaaUrl": "https://nyaa.si/?q=MSPD7UDLWMYO2IXTOE3WIKGHHPQUB7TT",
      "size": "NaN MB",
      "date": "21/3/2026, 22.03.34"
    },
    {
      "title": "Dead Account S01E11 The A-B Alliance 1080p CR WEB-DL AAC2.0 H 264-VARYG (Multi-Subs)",
      "link": "https://animetosho.org/view/dead-account-s01e11-b-alliance-1080p-cr-web.n2088701",
      "magnet": "magnet:?xt=urn:btih:525MMGABFBFI3X3KMFBTLDSFFRLO66M4&tr=http%3A%2F%2Fnyaa.tracker.wf%3A7777%2Fannounce&tr=https%3A%2F%2Ftracker.nekobt.to%2Fapi%2Ftracker%2Fpublic%2Fannounce&tr=udp%3A%2F%2Fopen.stealth.si%3A80%2Fannounce&tr=udp%3A%2F%2Ftracker.opentrackr.org%3A1337%2Fannounce&tr=udp%3A%2F%2Fexodus.desync.com%3A6969%2Fannounce&dn=Dead%20Account%20S01E11%20The%20A-B%20Alliance%201080p%20CR%20WEB-DL%20AAC2.0%20H%20264-VARYG%20%28Multi-Subs%29",
      "hash": "525MMGABFBFI3X3KMFBTLDSFFRLO66M4",
      "nyaaUrl": "https://nyaa.si/?q=525MMGABFBFI3X3KMFBTLDSFFRLO66M4",
      "size": "NaN MB",
      "date": "21/3/2026, 22.03.23"
    },
    {
      "title": "[Erai-raws] Trigun Stargaze - 11 [1080p CR WEB-DL AVC AAC][MultiSub][305EDED7]",
      "link": "https://animetosho.org/view/erai-raws-trigun-stargaze-11-1080p-cr-web.n2088700",
      "magnet": "magnet:?xt=urn:btih:GDUHJ4V7ZANVVA7MDOZDJVMHW7C4CW5I&tr=http%3A%2F%2Fnyaa.tracker.wf%3A7777%2Fannounce&tr=udp%3A%2F%2Fopen.stealth.si%3A80%2Fannounce&tr=udp%3A%2F%2Ftracker.opentrackr.org%3A1337%2Fannounce&tr=udp%3A%2F%2Ftracker.torrent.eu.org%3A451%2Fannounce&tr=udp%3A%2F%2Ftracker.tiny-vps.com%3A6969%2Fannounce&dn=%5BErai-raws%5D%20Trigun%20Stargaze%20-%2011%20%5B1080p%20CR%20WEB-DL%20AVC%20AAC%5D%5BMultiSub%5D%5B305EDED7%5D",
      "hash": "GDUHJ4V7ZANVVA7MDOZDJVMHW7C4CW5I",
      "nyaaUrl": "https://nyaa.si/?q=GDUHJ4V7ZANVVA7MDOZDJVMHW7C4CW5I",
      "size": "NaN MB",
      "date": "21/3/2026, 22.03.03"
    }
  ]
}