{
  "last_update": "8/4/2026, 19.03.48",
  "data": [
    {
      "title": "[Anitsu] 86 Eighty Six S01 [BD 1080p x265 FLAC] [DUAL] [SUB PT-BR ENG]",
      "link_tosho": "https://animetosho.org/view/anitsu-86-eighty-six-s01-bd-1080p-x265.n2095423",
      "nyaa_url": "https://nyaa.si/?q=VACXNASP6VOJV6FR2OUGSAFQT36ZOXYD",
      "size": "NaN MB",
      "date": "8/4/2026, 18.44.26"
    },
    {
      "title": "Porco Rosso (1992) 紅の豚 [12-bit 4:2:0 Decrypted MGVC BD ISO]",
      "link_tosho": "https://animetosho.org/view/porco-rosso-1992-12-bit-4-2-0.n2095418",
      "nyaa_url": "https://nyaa.si/?q=4XVKOXWZZAP77NHQO7AU5BCT2WKWDCM3",
      "size": "NaN MB",
      "date": "8/4/2026, 18.15.15"
    },
    {
      "title": "[Gecko] Cat Tales - S01E26 (うごく！ねこむかしばなし; Ugoku! Neko Mukashibanashi) [YTB.WEB-DL 1080P AVC, Opus, M-SUB][171E069F]",
      "link_tosho": "https://animetosho.org/view/gecko-cat-tales-s01e26-ugoku-neko-mukashibanashi-ytb.n2095417",
      "nyaa_url": "https://nyaa.si/?q=6XKC5FBYENJVBC4IJ24OVHTB5YDJQDGV",
      "size": "NaN MB",
      "date": "8/4/2026, 18.07.22"
    },
    {
      "title": "Bishoujo.Senshi.Sailor.Moon.Crystal.S03E10.MULTI.Audio.Sub[FRE][ENG][GER][SPA][POR][CHI][JPN].1080p.BDRip.CUSTOM.x264.PCM.EAC3-KuroNeko VOSTFR Pretty Guardian Sailor Moon Crystal Death Busters 美少女戦士セーラームーンCrystal　第３期＜デス・バスターズ編＞",
      "link_tosho": "https://animetosho.org/view/bishoujo-senshi-sailor-moon-crystal-s03e10-multi-audio.n2095416",
      "nyaa_url": "https://nyaa.si/?q=7TOJXWMOFUAZTXSAUFTG2OVGYUW7DEGB",
      "size": "NaN MB",
      "date": "8/4/2026, 18.07.02"
    },
    {
      "title": "[ToonsHub] Cat Tales S01E26 1080p LNTV WEB-DL AAC2.0 H.264 (Ugoku! Neko Mukashi Banashi, Multi-Subs)",
      "link_tosho": "https://animetosho.org/view/toonshub-cat-tales-s01e26-1080p-lntv-web-dl.n2095415",
      "nyaa_url": "https://nyaa.si/?q=7NKA7MYWZ7N3YKNJND7VLUDBUWWVM4BU",
      "size": "NaN MB",
      "date": "8/4/2026, 18.05.51"
    },
    {
      "title": "[BlackRabbit] Freezing (2011) - S02 [Bluray-1080p][Opus 2.0][Dual Audio][UNCENSORED][AV1]",
      "link_tosho": "https://animetosho.org/view/blackrabbit-freezing-2011-s02-bluray-1080p-opus-2.k10228063590156",
      "nyaa_url": "https://nyaa.si/?q=JGKKRHOBYR7FX5A3WKB7YZBTA5XWGQ76",
      "size": "NaN MB",
      "date": "8/4/2026, 17.09.33"
    },
    {
      "title": "[BlackRabbit] Freezing (2011) - S01 [Bluray-1080p][Opus 2.0][Dual Audio][UNCENSORED][AV1]",
      "link_tosho": "https://animetosho.org/view/blackrabbit-freezing-2011-s01-bluray-1080p-opus-2.k10228018846478",
      "nyaa_url": "https://nyaa.si/?q=RA2Q3GSRWEZ4Y7M5JKDP2DKWDPO3C2IO",
      "size": "NaN MB",
      "date": "8/4/2026, 17.06.38"
    },
    {
      "title": "[BlackRabbit] Vermeil in Gold (2022) - S01 [Bluray-1080p][Opus 2.0][Dual Audio][UNCENSORED][AV1]",
      "link_tosho": "https://animetosho.org/view/blackrabbit-vermeil-gold-2022-s01-bluray-1080p-opus.k10227649549321",
      "nyaa_url": "https://nyaa.si/?q=EHUUQOWYHPFFWPJTWQZR2MVZSRWVBRUQ",
      "size": "NaN MB",
      "date": "8/4/2026, 16.42.36"
    },
    {
      "title": "[BlackRabbit] Sekirei (2008) - S00 [Bluray-720p][Opus 2.0][Dual Audio][UNCENSORED][AV1]",
      "link_tosho": "https://animetosho.org/view/blackrabbit-sekirei-2008-s00-bluray-720p-opus-2.k10226655073799",
      "nyaa_url": "https://nyaa.si/?q=TYITDDUZCKLLR4ATZMW3K7XI3CTGXDMJ",
      "size": "NaN MB",
      "date": "8/4/2026, 15.37.51"
    },
    {
      "title": "[BlackRabbit] Sekirei (2008) - S02 [Bluray-1080p][Opus 2.0][Dual Audio][UNCENSORED][AV1]",
      "link_tosho": "https://animetosho.org/view/blackrabbit-sekirei-2008-s02-bluray-1080p-opus-2.k10226609157893",
      "nyaa_url": "https://nyaa.si/?q=RFWIHAYHRGPQW3FIWURGAVSGY7UIDRES",
      "size": "NaN MB",
      "date": "8/4/2026, 15.34.52"
    },
    {
      "title": "[BlackRabbit] Sekirei (2008) - S01 [Bluray-720p][Opus 2.0][Dual Audio][UNCENSORED][AV1]",
      "link_tosho": "https://animetosho.org/view/blackrabbit-sekirei-2008-s01-bluray-720p-opus-2.k10226557577736",
      "nyaa_url": "https://nyaa.si/?q=SFQYVVTNOQZQRJW5TZ775QXNUCTR3KLP",
      "size": "NaN MB",
      "date": "8/4/2026, 15.31.30"
    },
    {
      "title": "Macademi Wasshoi!.iso",
      "link_tosho": "https://animetosho.org/view/macademi-wasshoi-iso.n2095395",
      "nyaa_url": "https://nyaa.si/?q=WIVYOVNGVLA2R7LISJ5V4S5MDU6IXESN",
      "size": "NaN MB",
      "date": "8/4/2026, 15.29.52"
    },
    {
      "title": "[BlackRabbit] Yamada-kun and the Seven Witches (2015) - S00 [DVD-480p][Opus 2.0][AV1]",
      "link_tosho": "https://animetosho.org/view/blackrabbit-yamada-kun-seven-witches-2015-s00-dvd.k10226125283595",
      "nyaa_url": "https://nyaa.si/?q=2FFGL5KV5IR2UBV7SFSRWQTTHL5EY2LW",
      "size": "NaN MB",
      "date": "8/4/2026, 15.03.21"
    },
    {
      "title": "[BlackRabbit] Yamada-kun and the Seven Witches (2015) - S01 [Bluray-1080p][Opus 2.0][Dual Audio][AV1]",
      "link_tosho": "https://animetosho.org/view/blackrabbit-yamada-kun-seven-witches-2015-s01-bluray.k10226031073284",
      "nyaa_url": "https://nyaa.si/?q=ODM7WTB4WGSIUXADWEWKYWCFEWGL44QI",
      "size": "NaN MB",
      "date": "8/4/2026, 14.57.13"
    },
    {
      "title": "[BlackRabbit] Ladies Versus Butlers! (2010) - S00 [Bluray-1080p][Opus 2.0][UNCENSORED][AV1]",
      "link_tosho": "https://animetosho.org/view/blackrabbit-ladies-versus-butlers-2010-s00-bluray-1080p.k10225646969098",
      "nyaa_url": "https://nyaa.si/?q=55NOIHGCVPE25BSUWFSKBLDU5JWJOD27",
      "size": "NaN MB",
      "date": "8/4/2026, 14.32.13"
    }
  ]
}