{
  "last_update": "6/4/2026, 12.52.36",
  "data": [
    {
      "title": "[BlackRabbit] Midori (1992) [DVD-576p][Opus 2.0][UNCENSORED][AV1]",
      "link_tosho": "https://animetosho.org/view/blackrabbit-midori-1992-dvd-576p-opus-2-0-uncensored-av1.k10179758104577",
      "nyaa_url": "https://nyaa.si/?q=ZGOK6DWLTBHY6JA2R4MXOW2BERULEODI",
      "size": "NaN MB",
      "date": "6/4/2026, 12.44.40"
    },
    {
      "title": "[ToonsHub] Star Detective Precure S01E10 1080p CR WEB-DL AAC2.0 H.264 (Meitantei Precure!, Multi-Subs)",
      "link_tosho": "https://animetosho.org/view/toonshub-star-detective-precure-s01e10-1080p-cr-web.n2094663",
      "nyaa_url": "https://nyaa.si/?q=2UUOUEJRIVKEFAQNMYEFT7A2RGPW3N4U",
      "size": "NaN MB",
      "date": "6/4/2026, 12.32.33"
    },
    {
      "title": "[Erai-raws] Dorohedoro Season 2 - 03 [1080p NF WEBRip HEVC AAC][MultiSub][17A352FE]",
      "link_tosho": "https://animetosho.org/view/erai-raws-dorohedoro-season-2-03-1080p-nf.n2094657",
      "nyaa_url": "https://nyaa.si/?q=AVRXNSL6F6B34D6KMQIEVR7KSFE3RQG2",
      "size": "NaN MB",
      "date": "6/4/2026, 11.31.59"
    },
    {
      "title": "[Erai-raws] Dorohedoro Season 2 - 02 [1080p NF WEBRip HEVC AAC][MultiSub][3D5A0D11]",
      "link_tosho": "https://animetosho.org/view/erai-raws-dorohedoro-season-2-02-1080p-nf.n2094656",
      "nyaa_url": "https://nyaa.si/?q=IF5GB6FD7JULWJILOTYRONTBSOU2BMFX",
      "size": "NaN MB",
      "date": "6/4/2026, 11.31.02"
    },
    {
      "title": "[B00BA] Legendary Idol Eriko Season 1 (BD Remux 1080p x264 8-bit PCM) | Idol Densetsu Eriko",
      "link_tosho": "https://animetosho.org/view/b00ba-legendary-idol-eriko-season-1-bd-remux.n2094648",
      "nyaa_url": "https://nyaa.si/?q=V7QCRXRW4ZXATZPDIQFFJIKX2LMO5WXD",
      "size": "NaN MB",
      "date": "6/4/2026, 11.00.16"
    },
    {
      "title": "[ToonsHub] One Piece EP1156 2160p BILI WEB-DL AAC2.0 H.264 (Multi-Subs)",
      "link_tosho": "https://animetosho.org/view/toonshub-one-piece-ep1156-2160p-bili-web-dl.k10176339418126",
      "nyaa_url": "https://nyaa.si/?q=BHVJBWTMYVPO7GAR7LK7NXTQRGBEFLH7",
      "size": "NaN MB",
      "date": "6/4/2026, 09.02.05"
    },
    {
      "title": "[ToonsHub] One Piece EP1156 1080p BILI WEB-DL AAC2.0 H.265 (Multi-Subs)",
      "link_tosho": "https://animetosho.org/view/toonshub-one-piece-ep1156-1080p-bili-web-dl.k10176321589519",
      "nyaa_url": "https://nyaa.si/?q=KE3RZ3NOADQHAQTKY44GIQ3G23IXZN6T",
      "size": "NaN MB",
      "date": "6/4/2026, 09.00.56"
    },
    {
      "title": "[Beltraz] Reborn to Master the Blade: From Hero-King to Extraordinary Squire ♀ (2023) - S01 (BD 1080p HEVC FLAC) | Eiyuuou, Bu wo Kiwameru Tame Tenseisu: Soshite, Sekai Saikyou no Minarai Kishi ♀",
      "link_tosho": "https://animetosho.org/view/beltraz-reborn-master-blade-from-hero-king-extraordinary.k10176206086413",
      "nyaa_url": "https://nyaa.si/?q=HRWPAMAN2ZLWAZEY6REW6CYURYYFZDGD",
      "size": "NaN MB",
      "date": "6/4/2026, 08.53.25"
    },
    {
      "title": "[Erai-raws] Dorohedoro Season 2 - 01 [1080p NF WEBRip HEVC AAC][MultiSub][BAD24626]",
      "link_tosho": "https://animetosho.org/view/erai-raws-dorohedoro-season-2-01-1080p-nf.n2094568",
      "nyaa_url": "https://nyaa.si/?q=UJ67NPDHZER2MAEWNSGUZRWXXIW2QWHZ",
      "size": "NaN MB",
      "date": "6/4/2026, 08.04.34"
    },
    {
      "title": "[CrappySubs] Oshi no Ko - S03E11 - (WEB 1080p H.265 AAC) [ACF82930]",
      "link_tosho": "https://animetosho.org/view/crappysubs-oshi-no-ko-s03e11-web-1080p-h.k10175146155277",
      "nyaa_url": "https://nyaa.si/?q=RDTNL5RWSVQNLG3PDHSEVGHIHFM3PI7P",
      "size": "NaN MB",
      "date": "6/4/2026, 07.44.24"
    },
    {
      "title": "[Erai-raws] Seihantai na Kimi to Boku - 12 [1080p CR WEBRip HEVC AAC][MultiSub][DCF04EE8]",
      "link_tosho": "https://animetosho.org/view/erai-raws-seihantai-na-kimi-boku-12-1080p.n2094563",
      "nyaa_url": "https://nyaa.si/?q=NL3O2SQKWO4QABFPSPZA2Q4YXWX6UHEW",
      "size": "NaN MB",
      "date": "6/4/2026, 07.08.56"
    },
    {
      "title": "[Erai-raws] Seihantai na Kimi to Boku - 11 [1080p CR WEBRip HEVC AAC][MultiSub][0F8D623C]",
      "link_tosho": "https://animetosho.org/view/erai-raws-seihantai-na-kimi-boku-11-1080p.n2094562",
      "nyaa_url": "https://nyaa.si/?q=YCXSPSMLE6UCVL7PB7LLU7KFXU2CZ2JS",
      "size": "NaN MB",
      "date": "6/4/2026, 07.07.43"
    },
    {
      "title": "[Erai-raws] Oshi no Ko 3rd Season - 11 [1080p CR WEBRip HEVC AAC][MultiSub][AB4C93CD]",
      "link_tosho": "https://animetosho.org/view/erai-raws-oshi-no-ko-3rd-season-11.n2094561",
      "nyaa_url": "https://nyaa.si/?q=DK6VZ5PMLC2TE6XOVEGL7CW6AK7WTLNO",
      "size": "NaN MB",
      "date": "6/4/2026, 07.07.26"
    },
    {
      "title": "[Erai-raws] Osananajimi to wa LoveCom ni Naranai - 12 [1080p CR WEBRip HEVC AAC][MultiSub][1395873C]",
      "link_tosho": "https://animetosho.org/view/erai-raws-osananajimi-wa-lovecom-ni-naranai-12.n2094560",
      "nyaa_url": "https://nyaa.si/?q=3ZFNWBNLBLA2OXMTO75J6XSFHYTBNWZA",
      "size": "NaN MB",
      "date": "6/4/2026, 07.07.10"
    },
    {
      "title": "[Erai-raws] Omae Gotoki ga Maou ni Kateru to Omouna - 12 [1080p CR WEBRip HEVC AAC][MultiSub][0726DFDD]",
      "link_tosho": "https://animetosho.org/view/erai-raws-omae-gotoki-ga-maou-ni-kateru.n2094559",
      "nyaa_url": "https://nyaa.si/?q=V45YXQHLTQJMMDDAPWMRZRIGRUU2GJUT",
      "size": "NaN MB",
      "date": "6/4/2026, 07.06.53"
    }
  ]
}