{
  "last_update": "18/7/2026, 01.34.46",
  "data": [
    {
      "title": "[Ironclad] Tensei Shitara Slime Datta Ken 4 - S04E15 [WEB.1080p.AV1] | That Time I Got Reincarnated as a Slime (Multi-Subs) (Weekly)",
      "link_tosho": "https://animetosho.xyz/view/622391",
      "nyaa_url": "https://nyaa.si/view/2133927",
      "size": "290.51 MB",
      "date": "18/7/2026, 01.14.38"
    },
    {
      "title": "[ASW] Hell Mode S2 - 03 [1080p HEVC x265 10Bit][AAC]",
      "link_tosho": "https://animetosho.xyz/view/622392",
      "nyaa_url": "https://nyaa.si/view/2133926",
      "size": "360.04 MB",
      "date": "18/7/2026, 01.01.46"
    },
    {
      "title": "[Onalrie] Uchi no Otouto-domo ga Sumimasen - S01E03 [1080p WEBRip AV1]",
      "link_tosho": "https://animetosho.xyz/view/622390",
      "nyaa_url": "https://nekobt.to/torrents/12447064638222",
      "size": "166.32 MB",
      "date": "18/7/2026, 00.55.46"
    },
    {
      "title": "[ASW] Uchi no Otouto-domo ga Sumimasen - 03 [1080p HEVC x265 10Bit][AAC]",
      "link_tosho": "https://animetosho.xyz/view/622387",
      "nyaa_url": "https://nyaa.si/view/2133925",
      "size": "174.18 MB",
      "date": "18/7/2026, 00.49.46"
    },
    {
      "title": "[Judas] Yarikomizuki no Gamer wa Hai Settei no Isekai de Musou suru (Hell Mode The Hardcore Gamer Dominates in Another World with Garbage Balancing) - S02E03 [1080p][HEVC x265 10bit][Eng-Subs] (Weekly)",
      "link_tosho": "https://animetosho.xyz/view/622388",
      "nyaa_url": "https://nyaa.si/view/2133924",
      "size": "331.45 MB",
      "date": "18/7/2026, 00.49.32"
    },
    {
      "title": "[Breeze] Mushoku Tensei S03E03 [1080p AV1] Jobless Reincarnation (weekly)",
      "link_tosho": "https://animetosho.xyz/view/622389",
      "nyaa_url": "https://nyaa.si/view/2133923",
      "size": "769.35 MB",
      "date": "18/7/2026, 00.47.50"
    },
    {
      "title": "[Trix] The Drops of God S01E15 [WEBRip 1080p AV1 Opus] (Multi Subs, VOSTFR) | Kami no Shizuku 神の雫 (Weekly)",
      "link_tosho": "https://animetosho.xyz/view/622385",
      "nyaa_url": "https://nyaa.si/view/2133920",
      "size": "262.60 MB",
      "date": "18/7/2026, 00.32.55"
    },
    {
      "title": "[Erai-raws] Nige Jouzu no Wakagimi 2nd Season - 01 [1080p CR WEBRip HEVC AAC][MultiSub][EDCC2CCF]",
      "link_tosho": "https://animetosho.xyz/view/622386",
      "nyaa_url": "https://nyaa.si/view/2133919",
      "size": "746.42 MB",
      "date": "18/7/2026, 00.31.59"
    },
    {
      "title": "[Onalrie] Nige Jouzu no Wakagimi - S02E01 [1080p WEBRip AV1]",
      "link_tosho": "https://animetosho.xyz/view/622384",
      "nyaa_url": "https://nekobt.to/torrents/12446599467017",
      "size": "335.29 MB",
      "date": "18/7/2026, 00.25.29"
    },
    {
      "title": "[ASW] Nige Jouzu no Wakagimi S2 - 01 [1080p HEVC x265 10Bit][AAC]",
      "link_tosho": "https://animetosho.xyz/view/622380",
      "nyaa_url": "https://nyaa.si/view/2133912",
      "size": "577.69 MB",
      "date": "18/7/2026, 00.16.10"
    },
    {
      "title": "[Unfucked] The Elusive Samurai - S02E01 (1080p CR WEB-DL AVC AAC 2.0) [Multi-Subs] | Nige Jouzu no Wakagimi (2026)",
      "link_tosho": "https://animetosho.xyz/view/622381",
      "nyaa_url": "https://nyaa.si/view/2133910",
      "size": "1409.79 MB",
      "date": "18/7/2026, 00.13.04"
    },
    {
      "title": "[Unfucked] The Frontier Lord Begins with Zero Subjects - S01E03 (1080p CR WEB-DL AVC AAC 2.0) [Multi-Subs] | Ryoumin 0-nin Start no Henkyou Ryoushu-sama",
      "link_tosho": "https://animetosho.xyz/view/622382",
      "nyaa_url": "https://nyaa.si/view/2133909",
      "size": "1383.45 MB",
      "date": "18/7/2026, 00.13.01"
    },
    {
      "title": "[ASW] Kore Kaite Shine - 03 [1080p HEVC x265 10Bit][AAC]",
      "link_tosho": "https://animetosho.xyz/view/622383",
      "nyaa_url": "https://nyaa.si/view/2133908",
      "size": "318.16 MB",
      "date": "18/7/2026, 00.08.27"
    },
    {
      "title": "[Judas] Kore Kaite Shine (Draw This, Then Die!) - S01E03 [1080p][HEVC x265 10bit][Multi-Subs] (Weekly)",
      "link_tosho": "https://animetosho.xyz/view/622379",
      "nyaa_url": "https://nyaa.si/view/2133906",
      "size": "318.34 MB",
      "date": "17/7/2026, 23.57.18"
    },
    {
      "title": "[Onalrie] Kore Kaite Shine - S01E03 [1080p WEBRip AV1]",
      "link_tosho": "https://animetosho.xyz/view/622378",
      "nyaa_url": "https://nekobt.to/torrents/12446068780296",
      "size": "269.43 MB",
      "date": "17/7/2026, 23.50.56"
    }
  ]
}