{
  "last_update": "10/7/2026, 03.25.31",
  "data": [
    {
      "title": "[ASW] Tsuihou sareta Tensei Juukishi wa Game Chishiki de Musou suru - 02 [1080p HEVC x265 10Bit][AAC]",
      "link_tosho": "https://animetosho.xyz/view/620516",
      "nyaa_url": "https://nyaa.si/view/2130323",
      "size": "1135.29 MB",
      "date": "10/7/2026, 02.56.59"
    },
    {
      "title": "Angel's Egg (1985) (BDRip 1080p x265 HEVC OPUS)(Dual Audio)[MICO XD]",
      "link_tosho": "https://animetosho.xyz/view/620517",
      "nyaa_url": "https://nyaa.si/view/2130322",
      "size": "2774.83 MB",
      "date": "10/7/2026, 02.56.26"
    },
    {
      "title": "[VARYG] KAIJU GIRL CARAMELISE S01E02 1080p BILI WEB-DL AAC2.0 H.264 (Otome Kaijuu Caramelise, Multi-Subs)",
      "link_tosho": "https://animetosho.xyz/view/620513",
      "nyaa_url": "https://nekobt.to/torrents/12271915214603",
      "size": "398.30 MB",
      "date": "10/7/2026, 02.52.48"
    },
    {
      "title": "[VARYG] The Frontier Lord Begins with Zero Subjects S01E01 1080p BILI WEB-DL AAC2.0 H.264 (Ryoumin 0-Nin Start no Henkyou Ryoushu-sama, Multi-Subs)",
      "link_tosho": "https://animetosho.xyz/view/620514",
      "nyaa_url": "https://nekobt.to/torrents/12271901326601",
      "size": "300.78 MB",
      "date": "10/7/2026, 02.51.54"
    },
    {
      "title": "[ToonsHub] Star Blazers Space Battleship Yamato 3199 EP22 1080p CR WEB-DL AAC2.0 H.264 (Yamato yo Towa ni: REBEL3199, Multi-Subs)",
      "link_tosho": "https://animetosho.xyz/view/620508",
      "nyaa_url": "https://nyaa.si/view/2130319",
      "size": "1415.83 MB",
      "date": "10/7/2026, 02.48.16"
    },
    {
      "title": "[ToonsHub] Star Blazers Space Battleship Yamato 3199 EP21 1080p CR WEB-DL AAC2.0 H.264 (Yamato yo Towa ni: REBEL3199, Multi-Subs)",
      "link_tosho": "https://animetosho.xyz/view/620509",
      "nyaa_url": "https://nyaa.si/view/2130318",
      "size": "1416.08 MB",
      "date": "10/7/2026, 02.46.40"
    },
    {
      "title": "[ToonsHub] Star Blazers Space Battleship Yamato 3199 EP20 1080p CR WEB-DL AAC2.0 H.264 (Yamato yo Towa ni: REBEL3199, Multi-Subs)",
      "link_tosho": "https://animetosho.xyz/view/620510",
      "nyaa_url": "https://nyaa.si/view/2130317",
      "size": "1419.98 MB",
      "date": "10/7/2026, 02.45.38"
    },
    {
      "title": "[Erai-raws] Tsuihou sareta Tensei Juukishi wa Game Chishiki de Musou suru - 02 [1080p CR WEBRip HEVC AAC][MultiSub][204EDB41]",
      "link_tosho": "https://animetosho.xyz/view/620511",
      "nyaa_url": "https://nyaa.si/view/2130316",
      "size": "1053.77 MB",
      "date": "10/7/2026, 02.45.09"
    },
    {
      "title": "[ToonsHub] Star Blazers Space Battleship Yamato 3199 EP19 1080p CR WEB-DL AAC2.0 H.264 (Yamato yo Towa ni: REBEL3199, Multi-Subs)",
      "link_tosho": "https://animetosho.xyz/view/620512",
      "nyaa_url": "https://nyaa.si/view/2130315",
      "size": "1417.52 MB",
      "date": "10/7/2026, 02.45.07"
    },
    {
      "title": "[Onalrie] Tsuihou sareta Tensei Juukishi wa Game Chishiki de Musou suru - S01E02 [1080p WEBRip AV1]",
      "link_tosho": "https://animetosho.xyz/view/620515",
      "nyaa_url": "https://nekobt.to/torrents/12271718487816",
      "size": "829.58 MB",
      "date": "10/7/2026, 02.40.00"
    },
    {
      "title": "[jaaj] Clannad S01+S02+OVA (2007) (BD 1080p AV1 OPUS)",
      "link_tosho": "https://animetosho.xyz/view/620507",
      "nyaa_url": "https://nekobt.to/torrents/12271626297864",
      "size": "11886.03 MB",
      "date": "10/7/2026, 02.34.00"
    },
    {
      "title": "[ToonsHub] KAIJU GIRL CARAMELISE S01E02 1080p BILI WEB-DL AAC2.0 H.265 (Otome Kaijuu Caramelise, Multi-Subs)",
      "link_tosho": "https://animetosho.xyz/view/620506",
      "nyaa_url": "https://nyaa.si/view/2130311",
      "size": "371.12 MB",
      "date": "10/7/2026, 02.28.39"
    },
    {
      "title": "[BlackRabbit] Trapped in a Dating Sim - The World of Otome Games Is Tough for Mobs (2022) - S01 [Bluray-1080p][Opus 2.0][Dual Audio][AV1]",
      "link_tosho": "https://animetosho.xyz/view/620505",
      "nyaa_url": "https://nekobt.to/torrents/12271131972102",
      "size": "2187.84 MB",
      "date": "10/7/2026, 02.01.49"
    },
    {
      "title": "[ASW] Super no Ura de Yani Suu Futari - 01 [1080p HEVC x265 10Bit][AAC]",
      "link_tosho": "https://animetosho.xyz/view/620504",
      "nyaa_url": "https://nyaa.si/view/2130310",
      "size": "185.69 MB",
      "date": "10/7/2026, 02.00.02"
    },
    {
      "title": "[Erai-raws] Yani Neko - 02 [1080p NF WEBRip HEVC AAC][MultiSub][0CDB2A71]",
      "link_tosho": "https://animetosho.xyz/view/620501",
      "nyaa_url": "https://nyaa.si/view/2130309",
      "size": "614.75 MB",
      "date": "10/7/2026, 01.55.56"
    }
  ]
}