{
  "last_update": "24/4/2026, 01.09.03",
  "data": [
    {
      "title": "[Onalrie] Haibara-kun no Tsuyokute Seishun New Game - S01E04 [1080p WEBRip AV1].mkv",
      "link_tosho": "https://animetosho.org/view/onalrie-haibara-kun-no-tsuyokute-seishun-new-game.2076316",
      "nyaa_url": "https://nyaa.si/?q=66F6WJKJFZBIJV4WEYVB6DP2XWEQLNYW",
      "size": "NaN MB",
      "date": "24/4/2026, 01.02.00"
    },
    {
      "title": "[Freehold] Chained Soldier S02E07 REPACK2 [ADN WEB-DL 1080p x264 AAC EAC3 Dual-Audio Uncensored] | Mato Seihei no Slave Season 2",
      "link_tosho": "https://animetosho.org/view/freehold-chained-soldier-s02e07-repack2-adn-web-dl.k10567058784261",
      "nyaa_url": "https://nyaa.si/?q=WVX634F7LKUIJL7G2SCQ6FVTHFL665M3",
      "size": "NaN MB",
      "date": "24/4/2026, 00.59.33"
    },
    {
      "title": "[DKB] Koori no Jouheki - S01E04 [1080p][HEVC x265 10bit][Dual-Audio][Multi-Subs][weekly]",
      "link_tosho": "https://animetosho.org/view/dkb-koori-no-jouheki-s01e04-1080p-hevc-x265.n2101992",
      "nyaa_url": "https://nyaa.si/?q=THHKEK5B7PZJY2ZRJRQWYOK32R3PE5BJ",
      "size": "NaN MB",
      "date": "24/4/2026, 00.55.53"
    },
    {
      "title": "[Erai-raws] Reincarnation no Kaben - 04 [1080p AMZN WEBRip HEVC EAC3][2A701EED]",
      "link_tosho": "https://animetosho.org/view/erai-raws-reincarnation-no-kaben-04-1080p-amzn.k10566971666691",
      "nyaa_url": "https://nyaa.si/?q=GOUWCG2GBV27XEVQ64H4A3ITI5MJGBU7",
      "size": "NaN MB",
      "date": "24/4/2026, 00.53.53"
    },
    {
      "title": "Petals of Reincarnation S01E04 All-knowing and Corruption 1080p AMZN WEB-DL DDP2.0 H 264-VARYG (Reincarnation no Kaben, Multi-Subs)",
      "link_tosho": "https://animetosho.org/view/petals-reincarnation-s01e04-all-knowing-corruption-1080p.n2101990",
      "nyaa_url": "https://nyaa.si/?q=J2WIVVQUZQM6S6BIKAYMK5GPZ45ADVVW",
      "size": "NaN MB",
      "date": "24/4/2026, 00.40.53"
    },
    {
      "title": "[ToonsHub] Killed again Mr Detective S01E04 1080p CR WEB-DL AAC2.0 H.264 (Multi-Subs)",
      "link_tosho": "https://animetosho.org/view/toonshub-killed-again-mr-detective-s01e04-1080p-cr.k10566744582917",
      "nyaa_url": "https://nyaa.si/?q=BXJUOSVOWULZNEY52GKFFSRK2A3MBFRE",
      "size": "NaN MB",
      "date": "24/4/2026, 00.39.06"
    },
    {
      "title": "[Onalrie] Awajima Hyakkei - S01E03 [1080p WEBRip AV1].mkv",
      "link_tosho": "https://animetosho.org/view/onalrie-awajima-hyakkei-s01e03-1080p-webrip-av1-mkv.2076314",
      "nyaa_url": "https://nyaa.si/?q=UPASXQ7EVHOSX2A7URQXQJYRMXLBDALC",
      "size": "NaN MB",
      "date": "24/4/2026, 00.39.00"
    },
    {
      "title": "Monster Eater S01E04 1080p AMZN WEB-DL DDP2.0 H 264-VARYG (Mamonogurai no Boukensha: Ore Dake Mamono wo Kuratte Tsuyoku Naru, Multi-Subs)",
      "link_tosho": "https://animetosho.org/view/monster-eater-s01e04-1080p-amzn-web-dl-ddp2.n2101988",
      "nyaa_url": "https://nyaa.si/?q=JURV5KT64RFQ2MTYT7UFUHVXHLM3TTML",
      "size": "NaN MB",
      "date": "24/4/2026, 00.38.41"
    },
    {
      "title": "[ASW] Awajima Hyakkei - 03 [1080p HEVC x265 10Bit][AAC]",
      "link_tosho": "https://animetosho.org/view/asw-awajima-hyakkei-03-1080p-hevc-x265-10bit-aac.n2101987",
      "nyaa_url": "https://nyaa.si/?q=5YNH4JVRS46YSWBZWJ5E7Z4KM7SWOJ5R",
      "size": "NaN MB",
      "date": "24/4/2026, 00.36.49"
    },
    {
      "title": "[Gecko] Monster Eater - S01E04 (魔物喰らいの冒険者～俺だけ魔物を喰らって強くなる～; Mamonogurai no Boukensha: Ore dake Mamono wo Kuratte Tsuyoku Naru) [YTB.WEB-DL 1080P AVC, Opus, M-SUB][4788ACD7]",
      "link_tosho": "https://animetosho.org/view/gecko-monster-eater-s01e04-mamonogurai-no-boukensha-ore.k10566675722497",
      "nyaa_url": "https://nyaa.si/?q=Y7Y5KNZ4CVKD6YJQ443JJFJAG5QMNBMO",
      "size": "NaN MB",
      "date": "24/4/2026, 00.34.37"
    },
    {
      "title": "[ASW] Reincarnation no Kaben - 04 [1080p HEVC x265 10Bit][AAC]",
      "link_tosho": "https://animetosho.org/view/asw-reincarnation-no-kaben-04-1080p-hevc-x265-10bit-aac.n2101985",
      "nyaa_url": "https://nyaa.si/?q=4UU7HNFZO7YPLM2N2LVCNNJEBXCRYGXR",
      "size": "NaN MB",
      "date": "24/4/2026, 00.33.48"
    },
    {
      "title": "Killed again Mr Detective S01E04 The Kowloon Hotel Murderer Pt 1 1080p CR WEB-DL AAC2.0 H 264-VARYG (Mata Korosarete Shimatta no desu ne, Tantei-sama, Multi-Subs)",
      "link_tosho": "https://animetosho.org/view/killed-again-mr-detective-s01e04-kowloon-hotel-murderer.n2101983",
      "nyaa_url": "https://nyaa.si/?q=VXOI3KJAVHLZ4DE3JHKONWGS2GQ3PXVC",
      "size": "NaN MB",
      "date": "24/4/2026, 00.32.12"
    },
    {
      "title": "[SubsPlease] Mata Korosarete Shimatta no desu ne, Tantei-sama - 04 (1080p) [EA74ADA9].mkv",
      "link_tosho": "https://animetosho.org/view/subsplease-mata-korosarete-shimatta-no-desu-ne-tantei.n2101982",
      "nyaa_url": "https://nyaa.si/?q=SHDUSW62TC3SEMX7XNMD2IINNOS74BNY",
      "size": "NaN MB",
      "date": "24/4/2026, 00.32.09"
    },
    {
      "title": "[SubsPlease] Mata Korosarete Shimatta no desu ne, Tantei-sama - 04 (720p) [EB055761].mkv",
      "link_tosho": "https://animetosho.org/view/subsplease-mata-korosarete-shimatta-no-desu-ne-tantei.n2101978",
      "nyaa_url": "https://nyaa.si/?q=3FPQNY4TXFYT6TAWTWJE65AJSXFTINIE",
      "size": "NaN MB",
      "date": "24/4/2026, 00.31.38"
    },
    {
      "title": "[Erai-raws] Mata Korosarete Shimatta no desu ne, Tantei-sama - 04 [480p CR WEB-DL AVC AAC][MultiSub][BDC2EADA]",
      "link_tosho": "https://animetosho.org/view/erai-raws-mata-korosarete-shimatta-no-desu-ne.k10566623929871",
      "nyaa_url": "https://nyaa.si/?q=I6RLXH3WRWISY53C5G4ZSQWQ5TERKQD3",
      "size": "NaN MB",
      "date": "24/4/2026, 00.31.14"
    }
  ]
}