{
  "last_update": "6/5/2026, 03.45.35",
  "data": [
    {
      "title": "BEYBLADE X - 91 (1920x1080 - Cartoon Network CA)",
      "link_tosho": "https://animetosho.org/view/beyblade-x-91-1920x1080-cartoon-network-ca.k10834882083338",
      "nyaa_url": "https://nyaa.si/?q=6NYYRZFSZ4MWHE5GSVVCVT7NIWTXHGNX",
      "size": "NaN MB",
      "date": "6/5/2026, 03.35.58"
    },
    {
      "title": "[Erai-raws] Tadaima Ojamasaremasu - 05 [1080p CR WEBRip HEVC AAC][MultiSub][80F58619]",
      "link_tosho": "https://animetosho.org/view/erai-raws-tadaima-ojamasaremasu-05-1080p-cr-webrip.k10834297193985",
      "nyaa_url": "https://nyaa.si/?q=WPOUZL75EOTW2OX7WRYU7H7IIVQUAHQI",
      "size": "NaN MB",
      "date": "6/5/2026, 02.57.53"
    },
    {
      "title": "BEYBLADE X - 92 (1920x1080 - Cartoon Network CA)",
      "link_tosho": "https://animetosho.org/view/beyblade-x-92-1920x1080-cartoon-network-ca.k10834295781893",
      "nyaa_url": "https://nyaa.si/?q=W5HLT534EU7VC2YDX5RSZVBFUJHNWU4C",
      "size": "NaN MB",
      "date": "6/5/2026, 02.57.47"
    },
    {
      "title": "[DKB] Higeki no Genkyou to Naru Saikyou Gedou Last Boss Joou wa Tami no Tame ni Tsukushimasu. - S02E05 [HEVC x265 10bit][weekly]",
      "link_tosho": "https://animetosho.org/view/dkb-higeki-no-genkyou-naru-saikyou-gedou-last.n2106573",
      "nyaa_url": "https://nyaa.si/?q=F5TL5YYKJ4JAEP2NLYU2LNE5MXACX5HE",
      "size": "NaN MB",
      "date": "6/5/2026, 02.54.39"
    },
    {
      "title": "The Most Heretical Last Boss Queen From Villainess to Savior S02E05 1080p ADN WEB-DL AAC2.0 H 264-VARYG (Higeki no Genkyou to Naru Saikyou Gedou Last Boss Joou wa Tami no Tame ni Tsukus, Multi-Subs)",
      "link_tosho": "https://animetosho.org/view/most-heretical-last-boss-queen-from-villainess-savior.n2106572",
      "nyaa_url": "https://nyaa.si/?q=DOOCWTTEZGFWHRHIAHDUVHXHBDVGVEYB",
      "size": "NaN MB",
      "date": "6/5/2026, 02.53.12"
    },
    {
      "title": "[DKB] Class de 2-banme ni Kawaii Onnanoko to Tomodachi ni Natta - S01E05 [1080p][HEVC x265 10bit][Multi-Subs][weekly]",
      "link_tosho": "https://animetosho.org/view/dkb-class-de-2-banme-ni-kawaii-onnanoko.n2106571",
      "nyaa_url": "https://nyaa.si/?q=4QNCZWHGFLKF546ARUUQD3ASV7X6RINT",
      "size": "NaN MB",
      "date": "6/5/2026, 02.45.55"
    },
    {
      "title": "[Judas] Megami \"Isekai Tensei Nani ni Naritai desu ka\" Ore \"Yuusha no Rokkotsu de\" (My Ribdiculous Reincarnation) - S01E05 [1080p][HEVC x265 10bit][Multi-Subs] (Weekly)",
      "link_tosho": "https://animetosho.org/view/judas-megami-isekai-tensei-nani-ni-naritai-desu.n2106564",
      "nyaa_url": "https://nyaa.si/?q=EDHIE7DXVPK235OQNPAJ7BXLIPJD5WEH",
      "size": "NaN MB",
      "date": "6/5/2026, 02.24.42"
    },
    {
      "title": "[Lazyleido-Mini] DIGIMON BEATBREAK - 29 (S01E29) - (WEB 1080p AV1 10-bit AAC 2.0) [F61E4F1E]",
      "link_tosho": "https://animetosho.org/view/lazyleido-mini-digimon-beatbreak-29-s01e29-web-1080p.n2106548",
      "nyaa_url": "https://nyaa.si/?q=IAWV44OIUBIBUBDW3TMSJYIWX3KQ45GZ",
      "size": "NaN MB",
      "date": "6/5/2026, 02.09.39"
    },
    {
      "title": "[Lazyleido] DIGIMON BEATBREAK - 29 (S01E29) - (WEB 1080p HEVC x265 10-bit AAC 2.0) [8FD512A4]",
      "link_tosho": "https://animetosho.org/view/lazyleido-digimon-beatbreak-29-s01e29-web-1080p-hevc.n2106547",
      "nyaa_url": "https://nyaa.si/?q=2LWMYF2FMYOIYNNB37RIVA2DHJS5B5DA",
      "size": "NaN MB",
      "date": "6/5/2026, 02.09.36"
    },
    {
      "title": "BEYBLADE X - 94 (1920x1080 - Cartoon Network CA)",
      "link_tosho": "https://animetosho.org/view/beyblade-x-94-1920x1080-cartoon-network-ca.k10833535648774",
      "nyaa_url": "https://nyaa.si/?q=QQ427Q6EAOXUCCCYF6DNB2FXKWTYOIN2",
      "size": "NaN MB",
      "date": "6/5/2026, 02.08.18"
    },
    {
      "title": "[ASW] Yuusha no Rokkotsu de - 05 [1080p HEVC x265 10Bit][AAC]",
      "link_tosho": "https://animetosho.org/view/asw-yuusha-no-rokkotsu-de-05-1080p-hevc.n2106546",
      "nyaa_url": "https://nyaa.si/?q=UM6773TU4IHWTI3WHB3PIOPLYXU7OJTM",
      "size": "NaN MB",
      "date": "6/5/2026, 02.04.52"
    },
    {
      "title": "[Erai-raws] Marriagetoxin - 05 [1080p CR WEBRip HEVC AAC][MultiSub][6143EBC4]",
      "link_tosho": "https://animetosho.org/view/erai-raws-marriagetoxin-05-1080p-cr-webrip-hevc.k10833429855236",
      "nyaa_url": "https://nyaa.si/?q=TOGFFE7GQVNPY2AFJ7QQQTQNJAYTX6EF",
      "size": "NaN MB",
      "date": "6/5/2026, 02.01.25"
    },
    {
      "title": "[succ_] Tsugumomo (2017) - S01 (BD 1080p x264 10-bit Hi10P FLAC 2.0) [Dual-Audio] | つぐもも",
      "link_tosho": "https://animetosho.org/view/succ_-tsugumomo-2017-s01-bd-1080p-x264-10.n2106543",
      "nyaa_url": "https://nyaa.si/?q=OZYI4PRGZHHGQOQ2F42VDBZCW6ZW3RYJ",
      "size": "NaN MB",
      "date": "6/5/2026, 01.46.40"
    },
    {
      "title": "[Onalrie] Yuusha no Rokkotsu de - S01E05 [1080p WEBRip AV1].mkv",
      "link_tosho": "https://animetosho.org/view/onalrie-yuusha-no-rokkotsu-de-s01e05-1080p-webrip-av1-mkv.2079065",
      "nyaa_url": "https://nyaa.si/?q=BQ3EWTPVZ7CHXM645AKD4LRB46EJ6QPW",
      "size": "NaN MB",
      "date": "6/5/2026, 01.43.00"
    },
    {
      "title": "Cardfight!! Vanguard 15th Anniversary Remastered S01E03 (WEBDL 1080p x264 AAC) (Dual Audio) [S1PH3R]",
      "link_tosho": "https://animetosho.org/view/cardfight-vanguard-15th-anniversary-remastered-s01e03-webdl.n2106542",
      "nyaa_url": "https://nyaa.si/?q=JOW3H6IN6IOF5PWLJY7CYKCHQTILVWHF",
      "size": "NaN MB",
      "date": "6/5/2026, 01.41.54"
    }
  ]
}