{
  "last_update": "5/7/2026, 04.07.32",
  "data": [
    {
      "title": "[Trix] Mistress Kanan is Devilishly Easy S01 v2 (Batch) [WEBRip 1080p AV1 Opus] (Dual Audio, Multi Subs, VOSTFR) | Kanan-sama wa Akumade Choroi カナチョロ Is Easy as Hell! Season S1",
      "link_tosho": "https://animetosho.xyz/view/619415",
      "nyaa_url": "https://nyaa.si/view/2128406",
      "size": "4138.29 MB",
      "date": "5/7/2026, 03.44.59"
    },
    {
      "title": "[Onalrie] Saijo no Osewa - S01E01 [1080p WEBRip AV1]",
      "link_tosho": "https://animetosho.xyz/view/619417",
      "nyaa_url": "https://nekobt.to/torrents/12162078252558",
      "size": "179.26 MB",
      "date": "5/7/2026, 03.41.58"
    },
    {
      "title": "[ASW] Saijo no Osewa - 01 [1080p HEVC x265 10Bit][AAC]",
      "link_tosho": "https://animetosho.xyz/view/619416",
      "nyaa_url": "https://nyaa.si/view/2128404",
      "size": "196.76 MB",
      "date": "5/7/2026, 03.31.06"
    },
    {
      "title": "[Onalrie] Kimiai - S01E01 [1080p WEBRip AV1]",
      "link_tosho": "https://animetosho.xyz/view/619414",
      "nyaa_url": "https://nekobt.to/torrents/12161748000775",
      "size": "180.06 MB",
      "date": "5/7/2026, 03.20.28"
    },
    {
      "title": "Cardfight!! Vanguard 15th Anniversary Remastered S01E12 (WEBDL 1080p x264 AAC) (Dual Audio) [S1PH3R]",
      "link_tosho": "https://animetosho.xyz/view/619413",
      "nyaa_url": "https://nyaa.si/view/2128402",
      "size": "775.33 MB",
      "date": "5/7/2026, 03.14.24"
    },
    {
      "title": "[Onalrie] Mahou Shoujo Lyrical Nanoha EXCEEDS - Gun Blaze Vengeance - S01E01 [1080p WEBRip AV1]",
      "link_tosho": "https://animetosho.xyz/view/619411",
      "nyaa_url": "https://nekobt.to/torrents/12161357656330",
      "size": "633.60 MB",
      "date": "5/7/2026, 02.55.03"
    },
    {
      "title": "[TSPlease] Rich Girl Caretaker Im Secretly the Caregiver of the Most Popular Girl in This Rich Kid School S01E01 1080p CR WEB-DL AAC2.0 H.264 (Multi-Subs) | Saijo no Osewa: Takane no Hanadarake na Meimonkou de, Gakuin Ichi no Ojou-sama",
      "link_tosho": "https://animetosho.xyz/view/619410",
      "nyaa_url": "https://nyaa.si/view/2128401",
      "size": "1389.20 MB",
      "date": "5/7/2026, 02.50.45"
    },
    {
      "title": "[Nitsy] BanG Dream! Yume∞Mita - S01E02 (1080p WEB AAC x264).mkv",
      "link_tosho": "https://animetosho.xyz/view/619412",
      "nyaa_url": "https://nekobt.to/torrents/12161222750214",
      "size": "1386.05 MB",
      "date": "5/7/2026, 02.46.16"
    },
    {
      "title": "[ASW] Grow Up Show - Himawari no Circus-dan - 01 [1080p HEVC x265 10Bit][AAC]",
      "link_tosho": "https://animetosho.xyz/view/619406",
      "nyaa_url": "https://nyaa.si/view/2128394",
      "size": "318.67 MB",
      "date": "5/7/2026, 02.32.33"
    },
    {
      "title": "[ToonsHub] Rich Girl Caretaker Im Secretly the Caregiver of the Most Popular Girl in This Rich Kid School S01E01 1080p BILI WEB-DL AAC2.0 H.265 (Multi-Subs)",
      "link_tosho": "https://animetosho.xyz/view/619407",
      "nyaa_url": "https://nyaa.si/view/2128393",
      "size": "229.84 MB",
      "date": "5/7/2026, 02.31.53"
    },
    {
      "title": "[ASW] Tenmaku no Jaadugar - 02 [1080p HEVC x265 10Bit][AAC]",
      "link_tosho": "https://animetosho.xyz/view/619408",
      "nyaa_url": "https://nyaa.si/view/2128391",
      "size": "864.53 MB",
      "date": "5/7/2026, 02.30.56"
    },
    {
      "title": "[Erai-raws] Kabushikigaisha Magilumiere 2nd Season - 01 [1080p AMZN WEBRip HEVC EAC3][MultiSub][BACE4755]",
      "link_tosho": "https://animetosho.xyz/view/619409",
      "nyaa_url": "https://nyaa.si/view/2128388",
      "size": "296.67 MB",
      "date": "5/7/2026, 02.28.18"
    },
    {
      "title": "[ToonsHub] Rich Girl Caretaker Im Secretly the Caregiver of the Most Popular Girl in This Rich Kid School S01E01 1080p BILI WEB-DL AAC2.0 H.265 (Multi-Subs)",
      "link_tosho": "https://animetosho.xyz/view/619405",
      "nyaa_url": "https://nekobt.to/torrents/12160648346114",
      "size": "229.84 MB",
      "date": "5/7/2026, 02.08.52"
    },
    {
      "title": "[LoliHouse] 『你们先走我断后』，于是10年后我成为了传说 / Koko wa Ore ni Makasete Saki ni Ike to Itte kara 10-nen ga Tattara Densetsu ni Natteita. - 01 [WebRip 1080p HEVC-10bit AAC][无中字]",
      "link_tosho": "https://animetosho.xyz/view/619404",
      "nyaa_url": "https://nyaa.si/view/2128374",
      "size": "568.92 MB",
      "date": "5/7/2026, 02.03.58"
    },
    {
      "title": "[Onalrie] Oni no Hanayome - S01E01 [1080p WEBRip AV1]",
      "link_tosho": "https://animetosho.xyz/view/619403",
      "nyaa_url": "https://nekobt.to/torrents/12160503270914",
      "size": "152.00 MB",
      "date": "5/7/2026, 01.59.25"
    }
  ]
}