{
  "last_update": "9/7/2026, 21.05.51",
  "data": [
    {
      "title": "[Erai-raws] Reiwa no Dara-san - 02 [1080p CR WEBRip HEVC AAC][MultiSub][FD7963F7]",
      "link_tosho": "https://animetosho.xyz/view/620404",
      "nyaa_url": "https://nekobt.to/torrents/12266171510024",
      "size": "488.38 MB",
      "date": "9/7/2026, 20.38.52"
    },
    {
      "title": "[HuangSubs] The Demon Hunter Season 3 01-15 (1080p) | (沧元图 第三季, Cang Yuan Tu 3)",
      "link_tosho": "https://animetosho.xyz/view/620403",
      "nyaa_url": "https://nyaa.si/view/2130144",
      "size": "5234.22 MB",
      "date": "9/7/2026, 20.30.27"
    },
    {
      "title": "[BlackRabbit] Fate+Apocrypha (2017) - S01 [Bluray-1080p][Opus 2.0][Dual Audio][AV1]",
      "link_tosho": "https://animetosho.xyz/view/620405",
      "nyaa_url": "https://nekobt.to/torrents/12265998193409",
      "size": "3986.96 MB",
      "date": "9/7/2026, 20.27.35"
    },
    {
      "title": "[FuyuPOP] Buchigire Reijou wa Houfuku wo Chikaimashita - Ep01 (1080p x265 AAC WEB)",
      "link_tosho": "https://animetosho.xyz/view/620401",
      "nyaa_url": "https://nekobt.to/torrents/12265920954882",
      "size": "944.02 MB",
      "date": "9/7/2026, 20.22.33"
    },
    {
      "title": "[ASW] Reiwa no Dara-san - 02 [1080p HEVC x265 10Bit][AAC]",
      "link_tosho": "https://animetosho.xyz/view/620398",
      "nyaa_url": "https://nyaa.si/view/2130143",
      "size": "207.03 MB",
      "date": "9/7/2026, 20.20.10"
    },
    {
      "title": "[Judas] Reiwa no Dara-san (Dara-san of Reiwa) - S01E02 [1080p][HEVC x265 10bit][Multi-Subs] (Weekly)",
      "link_tosho": "https://animetosho.xyz/view/620399",
      "nyaa_url": "https://nyaa.si/view/2130142",
      "size": "214.39 MB",
      "date": "9/7/2026, 20.15.09"
    },
    {
      "title": "[Onalrie] Bungou Stray Dogs Wan! - S02E02 [1080p WEBRip AV1]",
      "link_tosho": "https://animetosho.xyz/view/620402",
      "nyaa_url": "https://nekobt.to/torrents/12265796391428",
      "size": "115.49 MB",
      "date": "9/7/2026, 20.14.27"
    },
    {
      "title": "[ASW] Bungou Stray Dogs Wan! S2 - 02 [1080p HEVC x265 10Bit][AAC]",
      "link_tosho": "https://animetosho.xyz/view/620400",
      "nyaa_url": "https://nyaa.si/view/2130141",
      "size": "155.29 MB",
      "date": "9/7/2026, 20.10.14"
    },
    {
      "title": "[ToonsHub] GANSO BanG Dream Chan S01E40 1080p AMZN WEB-DL DDP2.0 H.264 (Ganso! Bandori-chan, Multi-Subs)",
      "link_tosho": "https://animetosho.xyz/view/620395",
      "nyaa_url": "https://nyaa.si/view/2130140",
      "size": "63.34 MB",
      "date": "9/7/2026, 20.03.53"
    },
    {
      "title": "[Onalrie] Reiwa no Dara-san - S01E02 [1080p WEBRip AV1]",
      "link_tosho": "https://animetosho.xyz/view/620397",
      "nyaa_url": "https://nekobt.to/torrents/12265629806340",
      "size": "166.69 MB",
      "date": "9/7/2026, 20.03.36"
    },
    {
      "title": "[ToonsHub] Bungo Stray Dogs WAN S02E02 1080p AMZN WEB-DL DDP2.0 H.264 (Bungou Stray Dogs Wan!, Multi-Subs)",
      "link_tosho": "https://animetosho.xyz/view/620396",
      "nyaa_url": "https://nyaa.si/view/2130137",
      "size": "438.84 MB",
      "date": "9/7/2026, 19.55.49"
    },
    {
      "title": "[VARYG] Bungo Stray Dogs WAN S02E02 1080p CR WEB-DL AAC2.0 H.264 (Bungou Stray Dogs Wan!, Multi-Subs)",
      "link_tosho": "https://animetosho.xyz/view/620394",
      "nyaa_url": "https://nekobt.to/torrents/12265379319555",
      "size": "688.92 MB",
      "date": "9/7/2026, 19.47.17"
    },
    {
      "title": "[ToonsHub] Bungo Stray Dogs WAN S02E02 1080p CR WEB-DL AAC2.0 H.264 (Bungou Stray Dogs Wan!, Multi-Subs)",
      "link_tosho": "https://animetosho.xyz/view/620383",
      "nyaa_url": "https://nyaa.si/view/2130133",
      "size": "688.56 MB",
      "date": "9/7/2026, 19.44.19"
    },
    {
      "title": "[SubsPlease] Bungou Stray Dogs Wan! S2 - 02 (1080p) [FE1D50E4].mkv",
      "link_tosho": "https://animetosho.xyz/view/620384",
      "nyaa_url": "https://nyaa.si/view/2130131",
      "size": "683.59 MB",
      "date": "9/7/2026, 19.41.15"
    },
    {
      "title": "[Erai-raws] Bungou Stray Dogs Wan 2 - 02 [1080p CR WEB-DL AVC AAC][MultiSub][7EB07742]",
      "link_tosho": "https://animetosho.xyz/view/620389",
      "nyaa_url": "https://nyaa.si/view/2130125",
      "size": "688.36 MB",
      "date": "9/7/2026, 19.40.43"
    }
  ]
}