{
  "last_update": "17/6/2026, 02.51.45",
  "data": [
    {
      "title": "[Demo-subs] Sword Art Online Alternative - Gun Gale Online II - 11 (S02E11) (WEB 1080p AVC AAC) [AB5DB41E]",
      "link_tosho": "https://animetosho.xyz/view/616107",
      "nyaa_url": "https://nekobt.to/torrents/11762769640199",
      "size": "1430.15 MB",
      "date": "17/6/2026, 02.25.18"
    },
    {
      "title": "[Onalrie] Yuusha no Rokkotsu de - S01E11 [1080p WEBRip AV1]",
      "link_tosho": "https://animetosho.xyz/view/616108",
      "nyaa_url": "https://nekobt.to/torrents/11762741019650",
      "size": "568.96 MB",
      "date": "17/6/2026, 02.23.27"
    },
    {
      "title": "[Erai-raws] Higeki no Genkyou to Naru Saikyou Gedou Last Boss Joou wa Tami no Tame ni Tsukushimasu S02E11 [1080p ADN WEBRip HEVC AAC][MultiSub][ACA96763]",
      "link_tosho": "https://animetosho.xyz/view/616106",
      "nyaa_url": "https://nekobt.to/torrents/11762663364865",
      "size": "301.75 MB",
      "date": "17/6/2026, 02.18.23"
    },
    {
      "title": "[ASW] Yuusha no Rokkotsu de - 11 [1080p HEVC x265 10Bit][AAC]",
      "link_tosho": "https://animetosho.xyz/view/616104",
      "nyaa_url": "https://nyaa.si/view/2122346",
      "size": "809.20 MB",
      "date": "17/6/2026, 02.17.49"
    },
    {
      "title": "[Unfucked] I Made Friends with the Second Prettiest Girl in My Class - S01E11 (1080p CR WEB-DL AVC AAC 2.0) | Class de 2-banme ni Kawaii Onnanoko to Tomodachi ni Natta",
      "link_tosho": "https://animetosho.xyz/view/616105",
      "nyaa_url": "https://nyaa.si/view/2122344",
      "size": "1433.60 MB",
      "date": "17/6/2026, 02.09.10"
    },
    {
      "title": "[Unfucked] I Want to End This Love Game - S01E10 (1080p CR WEB-DL AVC AAC 2.0) | Aishiteru Game wo Owarasetai",
      "link_tosho": "https://animetosho.xyz/view/616103",
      "nyaa_url": "https://nyaa.si/view/2122341",
      "size": "1433.60 MB",
      "date": "17/6/2026, 01.56.29"
    },
    {
      "title": "[Onalrie] Tadaima, Ojamasaremasu! - S01E11 [1080p WEBRip AV1]",
      "link_tosho": "https://animetosho.xyz/view/616102",
      "nyaa_url": "https://nekobt.to/torrents/11762065854734",
      "size": "186.01 MB",
      "date": "17/6/2026, 01.39.29"
    },
    {
      "title": "[Unfucked] I Want to End This Love Game - S01E08 (1080p CR WEB-DL AVC AAC 2.0) [Dual-Audio] | Aishiteru Game wo Owarasetai",
      "link_tosho": "https://animetosho.xyz/view/616101",
      "nyaa_url": "https://nyaa.si/view/2122340",
      "size": "1433.60 MB",
      "date": "17/6/2026, 01.28.12"
    },
    {
      "title": "[ASW] Tadaima, Ojamasaremasu! - 11 [1080p HEVC x265 10Bit][AAC]",
      "link_tosho": "https://animetosho.xyz/view/616092",
      "nyaa_url": "https://nyaa.si/view/2122339",
      "size": "172.20 MB",
      "date": "17/6/2026, 01.25.25"
    },
    {
      "title": "My Ribdiculous Reincarnation S01E11 1080p CR WEB-DL AAC2.0 H 264-VARYG (Megami \"Isekai Tensei Nani ni Naritai Desu ka\" Ore \"Yuusha no Rokkotsu de\", Multi-Subs)",
      "link_tosho": "https://animetosho.xyz/view/616093",
      "nyaa_url": "https://nyaa.si/view/2122338",
      "size": "1331.20 MB",
      "date": "17/6/2026, 01.20.07"
    },
    {
      "title": "[SubsPlease] Yuusha no Rokkotsu de - 11 (1080p) [42B5307D].mkv",
      "link_tosho": "https://animetosho.xyz/view/616094",
      "nyaa_url": "https://nyaa.si/view/2122337",
      "size": "1331.20 MB",
      "date": "17/6/2026, 01.18.34"
    },
    {
      "title": "[ToonsHub] My Ribdiculous Reincarnation S01E11 1080p CR WEB-DL AAC2.0 H.264 (Megami \"Isekai Tensei Nani ni Naritai Desu ka\" Ore \"Yuusha no Rokkotsu de\", Multi-Subs)",
      "link_tosho": "https://animetosho.xyz/view/616096",
      "nyaa_url": "https://nyaa.si/view/2122333",
      "size": "1331.20 MB",
      "date": "17/6/2026, 01.17.38"
    },
    {
      "title": "[Erai-raws] Megami ~Isekai Tensei Nani ni Naritai Desu ka~ Ore ~Yuusha no Rokkotsu de~ - 11 [1080p CR WEB-DL AVC AAC][MultiSub][56E24679]",
      "link_tosho": "https://animetosho.xyz/view/616100",
      "nyaa_url": "https://nyaa.si/view/2122328",
      "size": "1331.20 MB",
      "date": "17/6/2026, 01.17.01"
    },
    {
      "title": "[ToonsHub] Above Myriads S01E04 1080p iQ WEB-DL AAC2.0 H.264 (Wan Ren Zhi Shang, Multi-Subs)",
      "link_tosho": "https://animetosho.xyz/view/616090",
      "nyaa_url": "https://nyaa.si/view/2122326",
      "size": "382.20 MB",
      "date": "17/6/2026, 01.02.53"
    },
    {
      "title": "[Erai-raws] Marriagetoxin - 11 [1080p CR WEBRip HEVC AAC][MultiSub][221AC173]",
      "link_tosho": "https://animetosho.xyz/view/616091",
      "nyaa_url": "https://nyaa.si/view/2122324",
      "size": "456.30 MB",
      "date": "17/6/2026, 00.56.49"
    }
  ]
}